Workbook

Sheet ThamSo
A1: Tham so tinh diem — SUA O CELL VANG, cac sheet khac tu tinh lai
A2: Trong so moi reply (W_REPLY) | B2: 1
A3: Trong so moi luot Ung (W_UNG) | B3: 2
A4: Do giam theo tuoi (GRAVITY, <1) | B4: 0.8
A5: Bu tuoi tinh theo gio (AGE_OFFSET_H) | B5: 6
A7: Diem goc = replies * W_REPLY + tong_Ung * W_UNG
A8: Hot score = Diem goc / (tuoi_thread_gio + AGE_OFFSET_H) ^ GRAVITY
A9: Nguon du lieu = https://voz.vn/f/diem-bao.33/ (page 1, da bo thread ghim)
A10: Thoi diem quet= 2026-10-04 15:55:06 +07
A11: Luu y: 'Ung' la reaction duy nhat cua voz (reaction id 1).
A12: Ban quyen: noi dung chi dung lam tu lieu tham khao/y tuong. Khong copy nguyen van comment cua nguoi khac len Threads.

Sheet Tong quan
A1: Hang | B1: Tieu de | C1: Link thread | D1: Link bai bao | E1: Nguon | F1: Replies | G1: Tong Ung | H1: Tuoi thread (gio) | I1: Diem goc | J1: Hot score | K1: So comment top | L1: Nguoi dang | M1: Thoi gian dang | N1: Trang da quet | O1: Trang thai | P1: Trich bai bao (post #1) | Q1: Loi
A2: =RANK(J2,$J$2:$J$21) | B2: Sẽ sửa thêm nhiều luật để GDP tăng trưởng 2 con số | C2: https://voz.vn/t/se-sua-them-nhieu-luat-de-gdp-tang-truong-2-con-so.1285462/ | D2: https://znews.vn/se-sua-them-nhieu-luat-de-gdp-tang-truong-2-con-so-post1686786.html | E2: znews.vn | F2: 139 | G2: 163 | H2: 4.85 | I2: =F2*ThamSo!$B$2+G2*ThamSo!$B$3 | J2: =IFERROR(I2/POWER(H2+ThamSo!$B$5,ThamSo!$B$4),0) | K2: 20 | L2: yoyovolam | M2: 2026-10-04 11:04 | N2: 7 | O2: ok | P2: Lãnh đạo Bộ Tài chính cho biết trong tháng 10, Chính phủ sẽ trình Quốc hội ban hành và sửa đổi rất nhiều luật để giải quyết vấn đề về thể chế, nhằm đạt mục tiêu tăng trưởng. Ngày 3/10, Cục Thống kê (Bộ Tài chính) đã công bố kết quả tăng trưởng kinh tế quý III và lũy kế 9 tháng của Việt nam với mức tăng lần lượt 9,95% và 9,01% so với cùng kỳ năm trước. Tính chung 9 tháng, đây là mức tăng trưởng kinh tế cao nhất trong vòng 15 năm trở lại đây. Dù ghi nhận kết quả tích cực ở nhiều chỉ số, thực tế mức tăng trưởng này vẫn chưa đạt mục tiêu 2 con số mà Chính phủ đề ra cho cả năm. Trong bối cảnh chỉ còn một quý cuối năm để hoàn tất nhiệm vụ, Chính phủ, Thủ tướng vẫn kiên định tiếp tục giữ mục tiêu tăng trưởng 2 con số năm nay. Còn một quý vẫn quyết đạt tăng trưởng 2 con số Chia sẻ tại phiên họp báo Chính phủ thường kỳ tháng 9 trưa nay, Thứ trưởng Bộ Tài chính Nguyễn Đức Chi một lần nữa khẳng định lại mục tiêu này và cho biết Thủ tướng cũng như Chính phủ đã chỉ đạo các bộ, ngành, địa phương tập trung thực hiện các giải pháp có hiệu quả, quyết liệt để từng bộ, địa phương, doanh nghiệp đều hoàn thành kế hoạch cả năm. Qua đó giúp toàn nền kinh tế đạt được mục tiêu tăng trưởng đề ra. tăng trưởng ảnh 1 Thứ trưởng Bộ Tài chính Nguyễn Đức Chi (đứng) thông tin về các giải pháp của Chính phủ để đạt mục tiêu tăng trưởng 2 con số năm nay. Ảnh: Chinhphu.vn/Nhật Bắc. Cụ thể, Chính phủ yêu cầu các bộ, cơ quan liên quan điều hành chủ động, linh hoạt, phối hợp chặt chẽ chính sách tiền tệ, tài khóa và các chính sách vĩ mô khác để kiểm soát lạm phát, góp phần ổn định kinh tế vĩ mô, hỗ trợ tăng trưởng kinh tế. Đảm bảo an ninh năng lượng, tuyệt đối không để nền kinh tế thiếu điện và thiếu xăng dầu. Bên cạnh đó, tiếp tục hoàn thiện thể chế và cải thiện môi trường đầu tư kinh doanh, tháo gỡ các vướng mắc về thể chế và không để phát sinh điểm nghẽn mới, cắt giảm thủ tục hành chính, điều kiện kinh doanh. Ngày trong tháng 10 này, Chính phủ sẽ trình Quốc hội ban hành và sửa đổi rất nhiều luật để giải quyết vấn đề về thể chế Thứ trưởng Bộ Tài chính Nguyễn Đức Chi “Ngày trong tháng 10 này, Chính phủ sẽ trình Quốc hội ban hành và sửa đổi rất nhiều luật để giải quyết vấn đề về thể chế”, Thứ trưởng Chi thông tin. Chính phủ cũng yêu cầu các bộ ngành, địa phương giải ngân 100% kế hoạch đầu tư công được giao, hoàn thành các dự án trọng điểm và tiến độ năm 2026. Trong đó, sẽ cắt giảm vốn của các bộ, địa phương giải ngân chậm để chuyển cho những dự án, những công trình có điều kiện và khả năng hấp thụ vốn. Tiếp tục triển khai các giải pháp giảm chi phí đầu vào cho nền kinh tế, thúc đẩy đầu tư tư nhân và tháo gỡ, triển khai các dự án tồn đọng. Trong đó hơn 1.000 dự án đã được giải quyết các khó khăn vướng mắc. Chính phủ chỉ đạo các bộ ngành cũng như các địa phương tập trung thực hiện vì đã được giải quyết về cơ chế nên phải tập trung triển khai. “Đây là động lực rất lớn để thúc đẩy tăng trưởng kinh tế. Các tập đoàn, tổng công ty Nhà nước có trách nhiệm tiếp tục hoàn thành kế hoạch sản xuất kinh doanh đã được xác định ngay từ đầu năm”, lãnh đạo Bộ Tài chính nói thêm. Ngoài ra, Chính phủ cũng yêu cầu các bộ ngành, địa phương ứng dụng khoa học, công nghệ, đổi mới sáng tạo, chuyển đổi số, thực hiện kế hoạch hành động 100 ngày giải ngân 100% vốn ngân sách Nhà nước đã dành cho khoa học công nghệ, đổi mới sáng tạo, chuyển đổi số trong 3 tháng cuối năm. “Bộ Tài chính luôn bám sát tình hình để tham mưu cho Chính phủ các kịch bản cũng như giải pháp để chúng ta hướng tới mục tiêu không thay đổi, đó là tăng trưởng hai con số về GDP trong năm 2026”, Thứ trưởng Nguyễn Đức Chi nhấn mạnh. Ngân hàng tăng cung ứng vốn cho nền kinh tế Cũng tại phiên họp báo, Phó thống đốc Ngân hàng Nhà nước Phạm Thanh Hà đã thông tin về hoạt động của hệ thống ngân hàng trong 3 quý đầu năm, định hướng điều hành chính sách tiền tệ quý cuối năm nhằm hỗ trợ nền kinh tế đạt mục tiêu tăng trưởng. Nguồn : Sẽ sửa thêm nhiều luật để GDP tăng trưởng 2 con số (https://znews.vn/se-sua-them-nhieu-luat-de-gdp-tang-truon…
A3: =RANK(J3,$J$2:$J$21) | B3: Giải Jackpot xổ số Mega 6/45 của Vietlott có thể tiến sát đỉnh 159 tỉ đồng | C3: https://voz.vn/t/giai-jackpot-xo-so-mega-6-45-cua-vietlott-co-the-tien-sat-dinh-159-ti-dong.1284286/ | D3: https://tuoitre.vn/giai-jackpot-xo-so-mega-6-45-cua-vietlott-co-the-tien-sat-dinh-159-ti-dong-100260930083548038.htm | E3: tuoitre.vn | F3: 655 | G3: 330 | H3: 100.41 | I3: =F3*ThamSo!$B$2+G3*ThamSo!$B$3 | J3: =IFERROR(I3/POWER(H3+ThamSo!$B$5,ThamSo!$B$4),0) | K3: 20 | L3: manoao | M3: 2026-09-30 11:30 | N3: 33 | O3: ok | P3: Giải Jackpot xổ số tự chọn Mega 6/45 của Vietlott dự báo sẽ đạt 155 tỉ đồng vào kỳ quay số mở thưởng ngày 30-9, tiến sát đỉnh 159 tỉ đồng từng ghi nhận tại kỳ quay số 00069. Jackpot xổ số tự chọn Mega 6/45 đang có giá trị cao chưa từng có trong năm 2026. - Ảnh: T.L Lần đầu tiên trong năm 2026, Jackpot của xổ số tự chọn Mega 6/45 tiến sát mốc 140 tỉ đồng. Sau khi tăng hơn 15,5 tỉ đồng ở kỳ quay gần nhất, giải thưởng này được dự báo có thể vượt 155 tỉ đồng tại kỳ quay số 01569 ngày 30-9. Nếu đạt mức này, Jackpot Mega 6/45 sẽ tiến sát mức 159 tỉ đồng từng ghi nhận tại kỳ quay số 00069. Người chơi có thể mua vé Mega 6/45 tại các điểm bán hàng Vietlott trên toàn quốc hoặc qua kênh phân phối bằng điện thoại với ứng dụng hỗ trợ Vietlott SMS. Tại điểm bán, người chơi người chơi có thể chọn sáu con số có hai chữ số từ 01 tới 45 trên phiếu, hoặc đọc cho người bán nhập vào máy. Mỗi vé có thể chứa nhiều bộ số, gồm cả số do người chơi tự chọn và số do máy tính chọn, mỗi bộ số giá 10.000 đồng. Giấy tô để mua vé số Vietlott tại điểm bán trực tiếp. - Ảnh: T.L Ngoài cách mua bộ số cơ bản như trên, người chơi cũng có thể lựa chọn hình thức "bao", từ "bao 5" đến "bao 18". Với "bao 5", người chơi chọn năm số, số còn lại được lấy lần lượt từ 40 số chưa chọn, tạo thành 40 bộ số. Giá vé là 400.000 đồng. Với "bao 7", "bao 8" đến "bao 18", người chơi chọn tương ứng 7 đến 18 số để tạo thành các bộ số dự thưởng. Cách chơi này được nhiều người lựa chọn mỗi khi Jackpot tăng cao như hiện nay. Vietlott SMS là kênh mua vé qua điện thoại của loại hình xổ số này. Người chơi có thể chọn số trên ứng dụng Vietlott SMS hoặc tại các điểm chạm trên một số ứng dụng ngân hàng điện tử, ví điện tử liên kết. Sau khi chọn Mega 6/45, người chơi có thể sử dụng các bộ số được hệ thống gợi ý để mua nhanh hoặc tự chọn lại từng bộ số mình muốn. Bước chọn số khi mua vé qua Vietlott SMS . - Ảnh: T.L Sau đó, người chơi chọn "Mua vé", lựa chọn "Kỳ hiện tại", "Đặt trước nhiều kỳ liên tiếp" hoặc "Đặt trước vé các kỳ tự chọn", rồi chọn "SMS Đặt vé" và gửi tin nhắn theo cú pháp được hệ thống soạn sẵn. Thao tác mua vé chỉ được tính là thành công khi nhận được tin nhắn trả về thông báo bộ số đã mua cùng đầy đủ thông tin của kỳ quay dự thưởng.
A4: =RANK(J4,$J$2:$J$21) | B4: [Dịch]Tàu thuyền xếp hàng chờ tiếp nhiên liệu tại cảng lớn nhất Trung quốc khi nguồn cung dầu bị siết chặt. Giá dầu ở đây đã cao hơn Singapore 25% | C4: https://voz.vn/t/dich-tau-thuyen-xep-hang-cho-tiep-nhien-lieu-tai-cang-lon-nhat-trung-quoc-khi-nguon-cung-dau-bi-siet-chat-gia-dau-o-day-da-cao-hon-singapore-25.1285464/ | D4: https://www.bloomberg.com/news/articles/2026-09-30/ships-face-fuel-delays-at-china-s-zhoushan-on-supply-squeeze | E4: bloomberg.com | F4: 68 | G4: 68 | H4: 4.79 | I4: =F4*ThamSo!$B$2+G4*ThamSo!$B$3 | J4: =IFERROR(I4/POWER(H4+ThamSo!$B$5,ThamSo!$B$4),0) | K4: 20 | L4: NDMan | M4: 2026-10-04 11:07 | N4: 4 | O4: ok | P4: [Bloomberg ngày 30 tháng 9 năm 2026] Các tàu thuyền đang phải chờ đợi lâu hơn đáng kể để tiếp nhiên liệu tại Trung tâm tiếp nhiên liệu hàng hải lớn nhất Trung Quốc ở Chu Sơn, nơi những hệ lụy từ cuộc chiến Mỹ - Iran đã làm thắt chặt nguồn cung và đẩy giá tăng cao. Theo các nguồn tin am hiểu vụ việc, một số tàu muốn nạp nhiên liệu tại cảng nằm ở phía nam Thượng Hải này đang phải đối mặt với thời gian chờ từ một đến hai tuần. Họ chia sẻ điều này với điều kiện ẩn danh vì không được phép phát ngôn với truyền thông, đồng thời cho biết thời gian chờ bình thường trước đây chỉ mất khoảng một đến hai ngày. Sự gián đoạn này phản ánh sự kết hợp giữa những hạn chế trong việc nhập khẩu dầu thô bắt nguồn từ xung đột ở Trung Đông, cùng với việc các nhà chế biến dầu Trung Quốc chuyển hướng diện rộng sang sản xuất xăng và dầu diesel nhằm thu về mức lợi nhuận hấp dẫn hơn. Điều đó đã dẫn đến việc cắt giảm sản lượng dầu FO (dầu nhiên liệu cặn), làm siết chặt nguồn cung của loại nhiên liệu thường được gọi là dầu hàng hải (bunker fuel). Cảng Ninh Ba - Chu Sơn hiện chưa đưa ra bình luận ngay lập tức về vấn đề này. Trung Quốc sẽ bước vào kỳ nghỉ lễ Quốc khánh kéo dài một tuần bắt đầu từ thứ Năm. Giá dầu hàng hải tại Chu Sơn vượt xa Singapore Theo dữ liệu từ đơn vị cung cấp giá nhiên liệu ClearLynx LLC, giá giao ngay của loại dầu hàng hải hàm lượng lưu huỳnh cực thấp (VLSFO) bán tại Chu Sơn vào thứ Ba đã tiến gần đến mức cao nhất kể từ tháng 3 — giai đoạn đầu của cuộc chiến Iran. Mức giá này cao hơn 25% so với giá bán cùng loại nhiên liệu tại Singapore, một trung tâm tiếp nhiên liệu đối thủ trong khu vực Châu Á. Dữ liệu từ đơn vị cung cấp thông tin năng lượng JLC cho thấy các nhà máy lọc dầu nhà nước của Trung Quốc đã sản xuất 1,12 triệu tấn dầu nhiên liệu hàm lượng lưu huỳnh thấp trong tháng 8, giảm 13% so với tháng 7. Tình trạng khan hiếm trên thị trường dầu nhiên liệu dự kiến sẽ hạ nhiệt vào đầu tháng 10, chủ yếu do nhu cầu sụt giảm theo mùa, trong khi hoạt động tiếp nhiên liệu tại nhiều cảng Trung Quốc cũng sẽ chậm lại trong suốt kỳ nghỉ lễ. Bắc Kinh từ lâu đã nỗ lực biến Chu Sơn thành một trung tâm tiếp nhiên liệu tầm cỡ khu vực để cạnh tranh với Singapore, dù quốc gia đảo quốc này hiện vẫn giữ vị thế dẫn đầu vượt trội về dịch vụ tiếp nhiên liệu cho tàu biển. Trung Quốc từng đưa ra chính sách hoàn thuế dầu nhiên liệu nhằm mang lại mức giá cạnh tranh để thu hút các đội tàu thương mại hướng đến Châu Á, đồng thời khuyến khích các nhà lọc dầu trong nước gia tăng sản lượng dầu nhiên liệu hàm lượng lưu huỳnh thấp. https://www.bloomberg.com/news/articles/2026-09-30/ships-face-fuel-delays-at-china-s-zhoushan-on-supply-squeeze
A5: =RANK(J5,$J$2:$J$21) | B5: Mazda CX-5 lại giảm giá, có đại lý chào bán từ 638 triệu đồng | C5: https://voz.vn/t/mazda-cx-5-lai-giam-gia-co-dai-ly-chao-ban-tu-638-trieu-dong.1285416/ | D5: https://dantri.com.vn/o-to-xe-may/mazda-cx-5-lai-giam-gia-co-dai-ly-chao-ban-tu-638-trieu-dong-20261003181844153.htm | E5: dantri.com.vn | F5: 87 | G5: 68 | H5: 8.89 | I5: =F5*ThamSo!$B$2+G5*ThamSo!$B$3 | J5: =IFERROR(I5/POWER(H5+ThamSo!$B$5,ThamSo!$B$4),0) | K5: 20 | L5: ChatGPT AI | M5: 2026-10-04 07:01 | N5: 5 | O5: ok | P5: (Dân trí) - Không phải đại lý nào cũng áp dụng mức giá khởi điểm ưu đãi 638 triệu đồng cho Mazda CX-5, phần lớn các showroom vẫn duy trì khuyến mại tương tự tháng trước.​ Càng gần tới thời điểm nâng cấp lên thế hệ mới (dự kiến vào tháng 11), Mazda CX-5 liên tục có mức giá “đáy” mới tại đại lý. Sang tháng 10, dòng xe này được nhà sản xuất hỗ trợ tới 100% lệ phí trước bạ. Tuy nhiên, theo tham khảo của phóng viên Dân trí, một đại lý tại miền Nam đang chào bán phiên bản tiêu chuẩn của mẫu C-SUV này với giá 638 triệu đồng, giảm tới 61 triệu đồng so với giá bán lẻ đề xuất. Với các phiên bản khác, đại lý báo giá như sau: Phiên bản Giá niêm yết Giá ưu đãi Mức giảm 2.0 Deluxe 699.000.000 638.000.000 61.000.000 2.0 Deluxe (tùy chọn) 749.000.000 679.000.000 70.000.000 2.0 Luxury 789.000.000 715.000.000 74.000.000 2.0 Premium Active 829.000.000 750.000.000 79.000.000 2.0 Premium Sport 849.000.000 769.000.000 80.000.000 2.0 Premium Exclusive 869.000.000 789.000.000 80.000.000 Giá bán thực tế của Mazda CX-5 tại một đại lý ở khu vực miền Nam áp dụng cho xe có đời sản xuất mới nhất (Đơn vị: đồng). Mức giá khởi điểm trên đã thấp hơn giá ưu đãi của một số mẫu SUV hạng B trên thị trường. Chẳng hạn, phiên bản cao cấp nhất của Mitsubishi Xforce (Ultimate) đang được nhà phân phối hỗ trợ 100% lệ phí trước bạ, tương đương mức giảm 72 triệu đồng, khiến giá bán thực tế giảm xuống còn 648 triệu đồng. Phiên bản tiêu chuẩn của Mazda CX-5 không có gói công nghệ an toàn chủ động như bản “full” của Xforce nhưng hàm lượng trang bị tiện nghi của xe vẫn khá phong phú. Bên cạnh đó, không gian rộng rãi của một mẫu SUV hạng C vẫn là yếu tố thu hút người dùng. Dù ưu đãi giảm giá sâu được áp dụng cho xe VIN 2026, tính thanh khoản vẫn bị ảnh hưởng do Mazda CX-5 sắp được nâng cấp lên thế hệ hoàn toàn mới (Ảnh: Nguyễn Hoàng). Không phải showroom nào cũng áp dụng mức giá ưu đãi như trên. Theo tìm hiểu của phóng viên Dân trí, phần lớn các đại lý tại khu vực miền Bắc vẫn duy trì mức giá khởi điểm thực tế trong khoảng 659-666 triệu đồng, giảm 33-40 triệu đồng so với giá niêm yết. Do đó, nếu quan tâm tới dòng xe này, người dùng nên tham khảo nhiều showroom để có thêm cơ sở so sánh và lựa chọn mức giá phù hợp. Khác với Mazda CX-5, đa số đối thủ cùng cỡ duy trì chương trình khuyến mại tương tự tháng trước. Ví dụ, Mitsubishi Destinator vẫn được nhà phân phối hỗ trợ 50-100% lệ phí trước bạ trong tháng 10. Mitsubishi Destinator được nhập khẩu nguyên chiếc từ Indonesia (Ảnh: Nhật Minh). Ford Territory được nhà sản xuất bổ sung ưu đãi cho phiên bản cao cấp nhất (Platinum) trong tháng 10, cụ thể là giảm giá 57 triệu đồng xuống còn 859 triệu đồng. Tuy nhiên, giá khởi điểm thực tế của mẫu xe này vẫn ở mức 665 triệu đồng, tương tự tháng trước, sau khi áp dụng mức hỗ trợ 100% lệ phí trước bạ.
A6: =RANK(J6,$J$2:$J$21) | B6: GDP quý IV phải tăng trên 12,5% để đạt mục tiêu tăng trưởng hai con số | C6: https://voz.vn/t/gdp-quy-iv-phai-tang-tren-12-5-de-dat-muc-tieu-tang-truong-hai-con-so.1285317/ | D6: https://vneconomy.vn/gdp-quy-iv-phai-tang-tren-125-de-dat-muc-tieu-tang-truong-hai-con-so.htm | E6: vneconomy.vn | F6: 97 | G6: 127 | H6: 22.53 | I6: =F6*ThamSo!$B$2+G6*ThamSo!$B$3 | J6: =IFERROR(I6/POWER(H6+ThamSo!$B$5,ThamSo!$B$4),0) | K6: 20 | L6: Cơ Bắp | M6: 2026-10-03 17:23 | N6: 5 | O6: ok | P6: Để đạt mục tiêu tăng trưởng hai con số trong năm 2026, GDP quý IV phải tăng trên 12,5%. Thủ tướng Lê Minh Hưng yêu cầu các bộ, ngành, địa phương quyết tâm cao nhất, khai thác tối đa dư địa tăng trưởng, đồng thời kiểm soát lạm phát, không tăng giá điện và bảo đảm tăng trưởng phục vụ lợi ích của người dân.​ Thủ tướng Chính phủ Lê Minh Hưng chủ trì phiên họp Chính phủ thường kỳ tháng 9/2026 và trực tuyến với các bộ, ngành, địa phương, tập trung đánh giá tình hình kinh tế - xã hội 9 tháng và xác định nhiệm vụ trọng tâm cho quý IV. Ảnh: Chinhphu.vn/Nhật Bắc Sáng 3/10, Thủ tướng Chính phủ Lê Minh Hưng chủ trì phiên họp Chính phủ thường kỳ tháng 9/2026 và trực tuyến với các bộ, ngành, địa phương, tập trung đánh giá tình hình kinh tế - xã hội 9 tháng và xác định nhiệm vụ trọng tâm cho quý IV. Kinh tế tiếp tục duy trì đà tăng trưởng cao. GDP quý III tăng 9,95%, đưa tăng trưởng 9 tháng lên 9,01%, mức cao nhất kể từ năm 2011. Sản xuất công nghiệp tăng trên 12%; tổng kim ngạch xuất nhập khẩu đạt 888 tỷ USD; vốn FDI đăng ký gần 50,4 tỷ USD, vốn thực hiện trên 21 tỷ USD. Giải ngân đầu tư công đạt gần 643 nghìn tỷ đồng, bằng 63% kế hoạch. Thu ngân sách nhà nước đạt 2,19 triệu tỷ đồng, gần 90% dự toán. CPI bình quân 9 tháng tăng 4,52%.
A7: =RANK(J7,$J$2:$J$21) | B7: [Dịch]Kinh tế suy yếu, bầu không khí u uất bao trùm khiến người dân Trung quốc đầy áp lực và bắt đầu trút giận lên nhau | C7: https://voz.vn/t/dich-kinh-te-suy-yeu-bau-khong-khi-u-uat-bao-trum-khien-nguoi-dan-trung-quoc-day-ap-luc-va-bat-dau-trut-gian-len-nhau.1285399/ | D7: https://www.nytimes.com/2026/10/02/opinion/china-anger-economic-frustration.html | E7: nytimes.com | F7: 81 | G7: 101 | H7: 16.29 | I7: =F7*ThamSo!$B$2+G7*ThamSo!$B$3 | J7: =IFERROR(I7/POWER(H7+ThamSo!$B$5,ThamSo!$B$4),0) | K7: 20 | L7: NDMan | M7: 2026-10-03 23:37 | N7: 5 | O7: ok | P7: [Nytimes ngày 2 tháng 10 năm 2026] Những năm gần đây, một bầu không khí ngày càng trở nên u uất bao trùm khắp Trung Quốc. Nền kinh tế suy yếu khiến nhiều người vỡ mộng — một trạng thái tâm lý được bộc lộ kín đáo cả trong đời sống riêng lẫn trên không gian mạng vốn bị kiểm soát gắt gao, qua những kỳ vọng bị hạ thấp và những mối lo âu thầm lặng. Giờ đây, một phần áp lực dồn nén đó dường như đang phát tiết ra ngoài theo những cách đáng lo ngại hơn. Vào tháng 3, một người đàn ông đã lái xe công trình hạng nặng tông thẳng vào một khu chợ ngoài trời ở ngoại thành Bắc Kinh, làm nhiều người thiệt mạng. Đến tháng 6, một chiếc máy bay nhỏ đã lao vào một tòa nhà văn phòng lớn ngay giữa thủ đô, khiến phi công thiệt mạng và 13 người khác bị thương trong một vụ việc nghi là tự sát. Và tháng trước, một người đàn ông đã bị bắt tại thành phố Quảng Châu ở phía nam sau khi dùng dao rạch mặt nhiều phụ nữ tại một khu mua sắm sầm uất. Những vụ việc như thế này vốn rất hiếm khi xảy ra tại Trung Quốc và bị kiểm duyệt cực kỳ gắt gao, khiến động cơ thực sự rất khó — nếu không muốn nói là không thể — xác định rõ ràng. Tuy nhiên, ở một quốc gia mà việc giải tỏa bức xúc trước các chính sách của chính quyền là điều nguy hiểm, tôi không thể xua đi cảm giác rằng người dân đang bắt đầu trút bỏ sự giận dữ và bất an lên chính những người xung quanh mình. Với quyết tâm cao độ trong cuộc cạnh tranh với Mỹ, Bắc Kinh đang dồn tổng lực vào việc phát triển các ngành công nghệ cao và sản xuất tiên tiến, coi đây là động lực cốt lõi cho sự tăng trưởng quốc gia trong tương lai. Trong cuộc gặp thượng đỉnh với Tổng thống Trump tại Nhà Trắng tuần trước, Chủ tịch Tập Cận Bình đã phát biểu đầy tự tin rằng Trung Quốc đang "mở ra những bước đột phá mới" trên con đường hiện đại hóa đất nước. Thế nhưng, diện mạo chung của nền kinh tế rộng lớn vẫn còn rất yếu ớt. Tỷ lệ thất nghiệp ở mức cao, đặc biệt là ở giới trẻ, còn tiền lương thì dậm chân tại chỗ. Các gia đình — vốn vẫn chưa hết bàng hoàng sau sự sụp đổ kéo dài của thị trường bất động sản — đang phải thắt lưng buộc bụng, cắt giảm chi tiêu. Năm nay, chính phủ đã đưa ra mục tiêu tăng trưởng kinh tế hàng năm ở mức thấp nhất kể từ năm 1991. Tâm lý muốn tìm ai đó để "đổ lỗi" thể hiện rõ qua hiện tượng bóc phốt (doxxing) lan truyền trên mạng có tên là "bá" (扒 - nghĩa là "vạch trần" hay "lột trần"). Trong những chiến dịch bóc phốt ngày càng dữ dội vài tháng qua, các nhóm "thám tử mạng" đã sục sạo, bới móc quá khứ của những cá nhân đột ngột nổi tiếng nhờ thành tích học tập hay nghề nghiệp, nhằm "lột trần" họ để tìm bằng chứng cho thấy họ tiến thân là nhờ quan hệ, gian lận hay sự ưu ái bất minh. Cuối tháng 7, Zhuge Yiyang — một nghiên cứu sinh tiến sĩ 29 tuổi tại Đại học Boston kiêm dẫn chương trình podcast — đã trở nên vô cùng nổi tiếng sau khi phỏng vấn đạo diễn Christopher Nolan về bộ phim "The Odyssey" . Cô từng được đông đảo người theo dõi trên mạng ngưỡng mộ như một biểu tượng cho thấy tài năng và sự chăm chỉ sẽ dẫn đến thành công, đồng thời nhận được vô số lời khen ngợi nhờ những câu hỏi sâu sắc, giàu trí tuệ trong buổi phỏng vấn. Tuy nhiên không lâu sau đó, làn sóng "vạch trần" trên mạng bùng nổ, kéo theo vô số cáo buộc rằng cô đã đạo văn trong các bài viết và nội dung podcast của mình. Mặc dù cô đã phủ nhận một số cáo buộc, cô vẫn phải hủy bỏ các buổi xuất hiện trước công chúng và chia sẻ rằng bản thân đã hoàn toàn kiệt quệ về mặt cảm xúc. Thường thì những sự dòm ngó này không xuất phát từ mong muốn vạch trần cái xấu, mà là sự hằn học theo bản năng hướng về giới "tinh hoa" — những người vô tình trở thành cái gai trong mắt một bộ phận công chúng đang thấy cơ hội tiến thân của chính mình ngày càng thu hẹp. Những "nạn nhân" gần đây rất đa dạng, từ một nữ diễn viên Trung Quốc, các bác sĩ danh tiếng, cho đến một nữ sinh tốt nghiệp Đại học Harvard — người từng gây chú ý vào năm ngoái khi trở thành người phụ nữ Trung Quốc đầu tiên phát biểu trong lễ tốt nghiệp của trường. Trong bài phát biểu của mình, cô gái trẻ đã kêu gọi sự đoàn k…
A8: =RANK(J8,$J$2:$J$21) | B8: Ngân hàng ngừng hỗ trợ chuyển khoản trên 10 triệu đồng với người dùng iPhone quá cũ | C8: https://voz.vn/t/ngan-hang-ngung-ho-tro-chuyen-khoan-tren-10-trieu-dong-voi-nguoi-dung-iphone-qua-cu.1285482/ | D8: https://thanhnien.vn/ngan-hang-ngung-ho-tro-chuyen-khoan-tren-10-trieu-dong-voi-nguoi-dung-iphone-qua-cu-185261004084816855.htm | E8: thanhnien.vn | F8: 40 | G8: 30 | H8: 2.68 | I8: =F8*ThamSo!$B$2+G8*ThamSo!$B$3 | J8: =IFERROR(I8/POWER(H8+ThamSo!$B$5,ThamSo!$B$4),0) | K8: 15 | L8: Knipex | M8: 2026-10-04 13:14 | N8: 3 | O8: ok | P8: Khách hàng sẽ không chuyển khoản được trên 10 triệu đồng khi sử dụng điện thoại iPhone đời quá cũ. Nhằm tăng cường bảo mật giao dịch số và hạn chế nguy cơ khách hàng bị lừa đảo công nghệ, Ngân hàng TMCP Tiên Phong (TPBank) thông báo từ ngày 1.11 sẽ ngừng hỗ trợ xác thực khuôn mặt trên ứng dụng TPBank và TPBank Biz đối với iPhone, iPad sử dụng iOS thấp hơn 16.7. Thay đổi này sẽ ảnh hưởng đến một số giao dịch yêu cầu khách hàng xác thực khuôn mặt trên ứng dụng ngân hàng. Cụ thể, với các giao dịch tài chính, khách hàng sử dụng thiết bị chưa đáp ứng yêu cầu về hệ điều hành có thể không thực hiện được xác thực khuôn mặt đối với các giao dịch chuyển khoản hoặc nạp ví điện tử trên 10 triệu đồng/lần hoặc có tổng hạn mức trên 20 triệu đồng/ngày. Các giao dịch thanh toán hóa đơn trên 100 triệu đồng/lần hoặc/ngày cũng thuộc nhóm bị ảnh hưởng.
A9: =RANK(J9,$J$2:$J$21) | B9: Lý do các đơn vị đồng loạt nâng dự báo tăng trưởng GDP Việt Nam | C9: https://voz.vn/t/ly-do-cac-don-vi-dong-loat-nang-du-bao-tang-truong-gdp-viet-nam.1285436/ | D9: https://tienphong.vn/ly-do-cac-don-vi-dong-loat-nang-du-bao-tang-truong-gdp-viet-nam-post1880728.tpo | E9: tienphong.vn | F9: 35 | G9: 43 | H9: 6.33 | I9: =F9*ThamSo!$B$2+G9*ThamSo!$B$3 | J9: =IFERROR(I9/POWER(H9+ThamSo!$B$5,ThamSo!$B$4),0) | K9: 17 | L9: BlueGecko | M9: 2026-10-04 09:35 | N9: 2 | O9: ok | P9: TPO - Ngân hàng Standard Chartered dự báo tăng trưởng GDP năm nay của Việt Nam ở mức 9,5%, còn Ngân hàng UOB Singapore dự báo tăng khoảng 8,5%. Standard Chartered dự báo tăng trưởng GDP năm 2026 ở mức 9,5%.
A10: =RANK(J10,$J$2:$J$21) | B10: Từ hôm nay, TP.HCM hứng đợt mưa lớn đến 6 ngày, có nơi trên 250 mm | C10: https://voz.vn/t/tu-hom-nay-tp-hcm-hung-dot-mua-lon-den-6-ngay-co-noi-tren-250-mm.1285437/ | D10: https://lifestyle.zingnews.vn/tu-hom-nay-tphcm-hung-dot-mua-lon-den-6-ngay-co-noi-tren-250-mm-post1687344.html | E10: lifestyle.zingnews.vn | F10: 51 | G10: 33 | H10: 6.21 | I10: =F10*ThamSo!$B$2+G10*ThamSo!$B$3 | J10: =IFERROR(I10/POWER(H10+ThamSo!$B$5,ThamSo!$B$4),0) | K10: 14 | L10: BrownGecko | M10: 2026-10-04 09:42 | N10: 3 | O10: ok | P10: Từ ngày 4 đến 9/10, TP.HCM được dự báo có mưa vừa, mưa to, có nơi mưa rất to. Tổng lượng mưa phổ biến 100-250 mm, có nơi trên 250 mm. Người dân cần đề phòng mưa lớn gây ngập lụt.​ Theo Trung tâm Dự báo Khí tượng Thủy văn Quốc gia, hôm nay 4/10, thời tiết Nam Bộ có mây, có mưa rào và dông vài nơi; riêng chiều tối và đêm có mưa rào và dông rải rác, cục bộ có nơi mưa to. Gió nhẹ. Trong mưa dông có khả năng xảy ra lốc, sét và gió giật mạnh. Tại TP.HCM, thời tiết ngày 4/10 có mây, có mưa rào và dông vài nơi; riêng chiều và tối có mưa rào và dông rải rác, cục bộ có nơi mưa to. Gió nhẹ. Trong mưa dông có khả năng xảy ra lốc, sét và gió giật mạnh. Nhiệt độ trong ngày dao động 24-34 độ C. Từ hôm nay, TP.HCM hứng đợt mưa lớn đến 6 ngày, có nơi trên 250 mm. Ảnh: Duy Hiệu.
A11: =RANK(J11,$J$2:$J$21) | B11: Kỷ nguyên năng suất mới của AI hiện thân: Việt Nam – Trụ cột Đông Nam Á | C11: https://voz.vn/t/ky-nguyen-nang-suat-moi-cua-ai-hien-than-viet-nam-tru-cot-dong-nam-a.1285452/ | D11: https://vtcnews.vn/ky-nguyen-nang-suat-moi-cua-ai-hien-than-viet-nam-tru-cot-dong-nam-a-ar1043094.html | E11: vtcnews.vn | F11: 38 | G11: 28 | H11: 5.19 | I11: =F11*ThamSo!$B$2+G11*ThamSo!$B$3 | J11: =IFERROR(I11/POWER(H11+ThamSo!$B$5,ThamSo!$B$4),0) | K11: 12 | L11: BrownGecko | M11: 2026-10-04 10:43 | N11: 2 | O11: ok | P11: (VTC News) - Hội nghị AI hiện thân Việt Nam lần thứ nhất diễn ra tại NIC Hòa Lạc với chủ đề “Kỷ nguyên năng suất mới của AI hiện thân: Việt Nam – Trụ cột Đông Nam Á”.​ Các đại biểu thực hiện nghi thức khai mạc Hội nghị. (Ảnh: Đỗ Huệ)
A12: =RANK(J12,$J$2:$J$21) | B12: Khu văn hóa du lịch tâm linh Giếng Tiên kinh phí trên 200 tỉ của nghệ sĩ Quyền Linh giờ ra sao ? | C12: https://voz.vn/t/khu-van-hoa-du-lich-tam-linh-gieng-tien-kinh-phi-tren-200-ti-cua-nghe-si-quyen-linh-gio-ra-sao.1285494/ | D12: https://tuoitre.vn/khu-van-hoa-du-lich-tam-linh-gieng-tien-kinh-phi-tren-200-ti-cua-nghe-si-quyen-linh-gio-ra-sao-10026100406574704.htm | E12: tuoitre.vn | F12: 22 | G12: 15 | H12: 1.29 | I12: =F12*ThamSo!$B$2+G12*ThamSo!$B$3 | J12: =IFERROR(I12/POWER(H12+ThamSo!$B$5,ThamSo!$B$4),0) | K12: 7 | L12: huycreative | M12: 2026-10-04 14:37 | N12: 2 | O12: ok | P12: Sau gần 6 năm khởi công, Khu văn hóa tín ngưỡng Giếng Tiên kinh phí trên 200 tỉ đồng của nghệ sĩ Quyền Linh ở Sóc Trăng cũ hiện vẫn chưa đưa vào hoạt động, cỏ mọc um tùm. Cổng chính Khu văn hóa du lịch tâm linh Giếng Tiên - Ảnh: KHẮC TÂM Ngày 4-10, một lãnh đạo xã Thuận Hòa, TP Cần Thơ cho biết so với kế hoạch ban đầu, dự án Khu văn hóa tín ngưỡng Giếng Tiên của nghệ sĩ Quyền Linh chậm tiến độ. Gần 6 năm sau ngày khởi công, vẫn chưa mở cửa đón khách​ Tháng 2-2020, Công ty Văn hóa - Du lịch Giếng Tiên Thảo Linh phối hợp UBND huyện Châu Thành, tỉnh Sóc Trăng cũ tổ chức lễ khởi công Khu văn hóa tín ngưỡng Giếng Tiên tại ấp Phước Thuận, xã Phú Tân (nay thuộc xã Thuận Hòa, TP Cần Thơ). Công ty Văn hóa - Du lịch Giếng Tiên Thảo Linh do ông Mai Huyền Linh (MC, nghệ sĩ Quyền Linh) làm giám đốc. Mục tiêu dự án này nhằm phục dựng lại truyền thuyết Giếng Tiên, vườn thiền, nhà trưng bày và ẩm thực văn hóa dân tộc , vườn tượng sáp các danh nhân văn hóa, khu phục dựng các phong tục tập quán của đồng bào dân tộc thiểu số… Ngã ba An Trạch thuộc quốc lộ 1 theo tỉnh lộ 932 khoảng 3km là đến Khu văn hóa tín ngưỡng Giếng Tiên. Từ ngoài nhìn vào, cổng chính có dòng chữ "Khu văn hóa du lịch tâm linh Giếng Tiên" khá lớn. Phía bên phải cổng vào có một chòi dựng tạm bợ để canh gác, ngay sau đó là một chiếc xe lu, một xe ủi có dấu hiệu nhiều ngày không hoạt động. Đi vào bên trong, quang cảnh càng hoang sơ, cỏ cây mọc um tùm. Phía bên phải có một hồ nước lớn. Bên trái có một số nhà mẫu, đều cửa đóng then cài, dây leo, cỏ mọc khá nhiều. Chòi canh "bảo vệ" từ cổng vào - Ảnh: KHẮC TÂM Một số nhà dây leo, cỏ mọc um tùm - Ảnh: KHẮC TÂM Nghệ sĩ Quyền Linh nói gì?​ Khu văn hóa du lịch tâm linh Giếng Tiên có quy mô gần 10ha, tổng vốn đầu tư trên 200 tỉ đồng, ban đầu dự kiến năm 2025 hoàn thành. Tuy nhiên gần 6 năm trôi qua, hiện dự án này vẫn chưa đi vào hoạt động. Trao đổi qua điện thoại, nghệ sĩ Quyền Linh cho biết mình thuê khu đất trên 50 năm và hiện có giao "mấy đứa em trông coi". "Linh cũng triển khai, nhưng do sau dịch COVID-19 có trục trặc về kinh tế. Dự kiến cuối năm 2026 hoặc đầu năm 2027, sẽ khởi động lại dự án", nghệ sĩ Quyền Linh cho hay. Một góc trong khu văn hóa - Ảnh: KHẮC TÂM Một lãnh đạo xã Thuận Hòa, TP Cần Thơ thông tin do khó khăn về tài chính nên ông Quyền Linh có đơn xin cắt giảm một số hạng mục. "Chúng tôi đã làm hồ sơ trình cấp thẩm quyền xem xét điều chỉnh", vị lãnh đạo xã nói. Theo vị này, dự án Khu văn hóa du lịch tâm linh Giếng Tiên rất được người dân quan tâm, mong muốn sớm đi vào hoạt động. "Địa phương chia sẻ khó khăn khách quan của nhà đầu tư, sẽ tạo điều kiện hỗ trợ. Khi hoạt động, còn kết nối với chùa Bốn Mặt, chùa Chăm Pa và làng nghề địa phương, chùa Pô Nô Rô Ca… tạo thành chuỗi các điểm đến độc đáo, đặc trưng của văn hóa đồng bào Khmer", vị lãnh đạo xã thông tin.
A13: =RANK(J13,$J$2:$J$21) | B13: (Mỹ) (Dịch) Ông Trump nói hối tiếc vì đã đề cử các thẩm phán Tòa án Tối cao Gorsuch, Barrett và Kavanaugh | C13: https://voz.vn/t/my-dich-ong-trump-noi-hoi-tiec-vi-da-de-cu-cac-tham-phan-toa-an-toi-cao-gorsuch-barrett-va-kavanaugh.1285422/ | D13: https://www.reuters.com/legal/government/trump-says-he-regrets-nominating-supreme-court-justices-gorsuch-barrett-2026-10-01/ | E13: reuters.com | F13: 17 | G13: 32 | H13: 7.62 | I13: =F13*ThamSo!$B$2+G13*ThamSo!$B$3 | J13: =IFERROR(I13/POWER(H13+ThamSo!$B$5,ThamSo!$B$4),0) | K13: 11 | L13: Mr_nam199z | M13: 2026-10-04 08:17 | N13: 1 | O13: ok | P13: WASHINGTON, ngày 1 tháng 10 (Reuters) - Tổng thống Mỹ Donald Trump cho biết ông hối tiếc vì đã đề cử ba thẩm phán Tòa án Tối cao —Neil Gorsuch, Amy Coney Barrett và Brett Kavanaugh — những người đã phản đối ông trong các phán quyết gần đây, theo một cuộc phỏng vấn với tạp chí Time. "Ông có hối hận vì đã đề cử họ không?" Người phỏng vấn hỏi, đề cập đến những bình luận của Trump trong một bài đăng gần đây trên Truth Social. "Vâng." "Đúng vậy," ông Trump trả lời, theo bản ghi chép cuộc phỏng vấn. "Tôi có thể làm gì?" Tôi đã đặt họ vào.Họ đã bỏ phiếu chống lại tôi quá nhiều lần. Tôi đã trao cho họ vị trí quan trọng nhất trong đời, vậy mà họ lại thường xuyên bỏ phiếu chống lại tôi." Ông Trump đã bổ nhiệm Gorsuch, Kavanaugh và Barrett trong nhiệm kỳ tổng thống đầu tiên của mình, tạo nên đa số bảo thủ 6-3 và cho phép tòa án định hướng theo hướng cánh hữu mạnh mẽ kể từ năm 2020. "Tôi thích sự trung thành, đúng vậy," Trump nói với người phỏng vấn, người sau đó hỏi liệu đó có phải là điều ông muốn từ các thẩm phán hay không. "Không, tôi không muốn lòng trung thành." "Tôi muốn có những quyết định đúng đắn," ông Trump nói. Sau khi cơ quan tư pháp cao nhất của Mỹ từ chối cho phép một quy định của Bưu điện hạn chế việc sử dụng phiếu bầu qua thư trong cuộc bầu cử giữa nhiệm kỳ tháng 11, ông Trump nói rằng những người được ông bổ nhiệm đã hành xử khác so với trong các cuộc phỏng vấn. "Đây không phải là những người tôi đã phỏng vấn để phục vụ tại Tòa án Tối cao Hoa Kỳ, họ chỉ là cái vỏ rỗng của chính bản thân họ," ông viết trên Truth Social. Sau khi tòa án hồi tháng Hai bác bỏ các mức thuế quan toàn cầu hà khắc mà họ cho là ông đã áp đặt bất hợp pháp bằng một đạo luật dành cho các trường hợp khẩn cấp quốc gia, Trump đã dành sự chỉ trích đặc biệt cho Gorsuch và Barrett, những người chiếm đa số trong phán quyết 6-3 đó. https://www.reuters.com/legal/government/trump-says-he-regrets-nominating-supreme-court-justices-gorsuch-barrett-2026-10-01/
... A21: =RANK(J21,$J$2:$J$21) | B21: Bầu cử Tổng thống Brazil: Hai ứng cử viên bám đuổi sít sao | C21: https://voz.vn/t/bau-cu-tong-thong-brazil-hai-ung-cu-vien-bam-duoi-sit-sao.1285496/ | D21: https://baotintuc.vn/bau-cu-tong-thong-brazil-hai-ung-cu-vien-bam-duoi-sit-sao-post1391253.html | E21: baotintuc.vn | F21: 5 | G21: 0 | H21: 1.2 | I21: =F21*ThamSo!$B$2+G21*ThamSo!$B$3 | J21: =IFERROR(I21/POWER(H21+ThamSo!$B$5,ThamSo!$B$4),0) | K21: 0 | L21: Riokuza | M21: 2026-10-04 14:43 | N21: 1 | O21: ok | P21: Tổng thống Brazil Lula da Silva và nghị sĩ Flávio Bolsonaro đã kết thúc chiến dịch vận động tranh cử trước thềm cuộc bầu cử tổng thống, dự kiến diễn ra vào ngày 4/10 theo giờ địa phương. Tổng thống Brazil Lula da Silva (giữa) trong cuộc vận động tranh cử tại thành phố Sao Paulo, ngày 3/10/2026. Ảnh: THX/TTXVN phát Theo phóng viên TTXVN tại Nam Mỹ, tại thành phố São Paulo, Tổng thống Lula da Silva, ứng cử viên của Đảng Lao động (PT), dẫn đầu đoàn xe vận động trong sự tham gia của đông đảo người ủng hộ mặc trang phục màu đỏ. Ông nhấn mạnh thông điệp bảo vệ chủ quyền quốc gia, đồng thời kêu gọi cử tri ủng hộ ông ngay từ vòng một. Đây cũng là nơi ông Lula từng kết thúc chiến dịch tranh cử năm 2022 trước khi đánh bại cựu Tổng thống Jair Bolsonaro ở vòng hai. Trong khi đó, ông Flávio Bolsonaro, ứng cử viên của Đảng Tự do (PL) và là con trai ông Jair Bolsonaro, dẫn đầu đoàn xe với hàng trăm người đi mô tô cũng tại bang São Paulo. Trong thông điệp cuối cùng trước cuộc bầu cử, chính trị gia 45 tuổi kêu gọi cử tri lựa chọn sự thay đổi ngay trong vòng một, qua đó tránh phải tiến hành vòng hai. Nghị sĩ Flavio Bolsonaro trong cuộc vận động tranh cử tại thành phố Rio de Janeiro, Brazil, ngày 22/8/2026. Ảnh: THX/TTXVN phát

Sheet Top comments
A1: Hang thread | B1: Tieu de thread | C1: Link bai bao | D1: Hang comment | E1: Ung | F1: Tac gia | G1: Post # | H1: Link comment | I1: Thoi gian | J1: Noi dung comment
A2: 1 | B2: Sẽ sửa thêm nhiều luật để GDP tăng trưởng 2 con số | C2: https://znews.vn/se-sua-them-nhieu-luat-de-gdp-tang-truong-2-con-so-post1686786.html | D2: 1 | E2: 3 | F2: Trư Bát Giới͏ | G2: 2 | H2: https://voz.vn/p/43907649/ | I2: 2026-10-04 11:05 | J2: Sửa số cho lẹ!!!
A3: 1 | B3: Sẽ sửa thêm nhiều luật để GDP tăng trưởng 2 con số | C3: https://znews.vn/se-sua-them-nhieu-luat-de-gdp-tang-truong-2-con-so-post1686786.html | D3: 2 | E3: 3 | F3: long020994v3 | G3: 3 | H3: https://voz.vn/p/43907658/ | I3: 2026-10-04 11:06 | J3: ể?
A4: 1 | B4: Sẽ sửa thêm nhiều luật để GDP tăng trưởng 2 con số | C4: https://znews.vn/se-sua-them-nhieu-luat-de-gdp-tang-truong-2-con-so-post1686786.html | D4: 3 | E4: 3 | F4: God of Moon | G4: 5 | H4: https://voz.vn/p/43907667/ | I4: 2026-10-04 11:07 | J4: Công bố GDP 2 con số, ai thắc mắc hay tò mò hỏi thì liên hệ conan phường tư vấn cho, sửa luật làm ccc gì có mệt vậy? Được gửi từ myVOZ Next trên iPhone
A5: 1 | B5: Sẽ sửa thêm nhiều luật để GDP tăng trưởng 2 con số | C5: https://znews.vn/se-sua-them-nhieu-luat-de-gdp-tang-truong-2-con-so-post1686786.html | D5: 4 | E5: 3 | F5: darkkong | G5: 6 | H5: https://voz.vn/p/43907669/ | I5: 2026-10-04 11:07 | J5: Thực sự rất lo ngại khi xứ này đang dần biến tướng giống Liên Xô 50 năm trước đây, khi mà cấp trên duy ý chí, ra chỉ tiêu tăng trưởng vô lý. Cấp dưới thì sợ hãi bị xử lý nên cố gắng làm giả tạo mọi số liệu để lấy lòng cấp trên. Hậu quả thật khủng khiếp, những năm 1980, Liên Xô với diện tích rộng 22 triệu km2, chiếm 1/6 diện tích Trái Đất, rộng lớn đến bao la bát ngát trải dài tới tận 2 bờ Đại dương, chim bay mỏi rã cánh, rơi xuống đất chết vì kiệt sức mà còn chưa bay hết 1/10 chiều dài lãnh thổ Liên Xô. Sở hữu diện tích đất nông nghiệp lớn nhất thế giới, đất canh tác trồng trọt rộng hơn các quốc gia khác cả trăm lần , v ậy mà sau mới lòi ra là thiếu lương thực, phải nhập khẩu lương thực từ các nước khác về thì mới đủ ăn mặc dù dân số Liên Xô ko lớn. Dân số Liên Xô hồi đó t 170tr dân, còn chưa bằng dân số Bangladesh hiện nay. Cái nhục nhã nhất là quan chức LX phải đi nhập khẩu lương thực từ Mỹ - quốc gia địch thủ của mình, cho thấy sự yếu kém trong cách quản lý kinh tế của chế độ XHCN, nhưng vẫn ngoan cố che giấu việc nhập khẩu lương thực từ nước Mỹ Tư bản ko là người dân phẫn nộ nổi dậy ngay. Hôm nay là ASIAD 2026 kết thúc tại Nhật đây, dân mạng chửi với phẫn nộ quá trời, đc có 3 HCV, trong khi những năm trc còn dc 4,5 HCV, năm nay thằng Thái nó tận 18 HCV, gấp 6 lần xứ lừa luôn. Bóng đá VN vừa rồi thua Thái Lan thảm bại 0-2 lun. Ai đời đi thi đấu, thành tích năm sau lại thua năm trc, càng ngày càng tụt lùi đi. Trên FB, Youtube, tôi thấy có mấy bình luận của người Thái Lan nói: Ít ra chính phủ chúng tôi minh bạch và trung thực với người dân. Số liệu bao nhiêu thì công bố bằng đấy. Năm nay GDP Thái Lan dc dự báo tăng trưởng 2,5% nhưng dân Thái Lan chúng tôi tin là số liệu thật. Còn các bạn VN cẩn thận với số liệu GDP 10% mà chính phủ các bạn công bố đó. ============= Các bạn đi làm ở các cty tư nhân ý, nếu bạn ko làm dc việc, ko đạt KPI đề ra, kết quả làm việc yếu kém, thì thằng Sếp chả sa thải, kỷ luật bạn, thậm chí đuổi tống cổ bạn ngay ý chứ. Nhưng ko, ở bình diện quốc gia, chúng ta đang chứng kiến Điều đáng sợ nhất ở VN là: thi đấu kết quả thảm bại, nhưng quan chức thì thấy đó là điều đương nhiên. Ko 1 thằng quan chức nào thấy bận tâm, ko ai thấy xấu hổ, ko ai từ chức cả. Chúng nó chỉ đơn giản xin lỗi 1 câu là xong. Rồi vài ngày sau, sẽ chẳng ai nhớ tới nữa. Và chúng nó vẫn tiếp tục ngồi ghế để kiếm chác, tham nhũng, ăn chặn tiền của VĐV chứ nhất quyết không chịu nhả ghế đang kiếm bẫm. Ở cái Xứ Lừa độc tài độc đảng này, chả có bên thứ 3 nào đứng ra giám sát, thì trong nước chúng nó tha hồ bốc phét làm giả số liệu GDP đc, chứ ra ngoài quốc tế, chúng nó biết ko thể làm giả số HC Vàng đc thì đành chịu.
A6: 1 | B6: Sẽ sửa thêm nhiều luật để GDP tăng trưởng 2 con số | C6: https://znews.vn/se-sua-them-nhieu-luat-de-gdp-tang-truong-2-con-so-post1686786.html | D6: 5 | E6: 3 | F6: auster | G6: 7 | H6: https://voz.vn/p/43907672/ | I6: 2026-10-04 11:08 | J6: Hầy
A7: 1 | B7: Sẽ sửa thêm nhiều luật để GDP tăng trưởng 2 con số | C7: https://znews.vn/se-sua-them-nhieu-luat-de-gdp-tang-truong-2-con-so-post1686786.html | D7: 6 | E7: 3 | F7: Ông Tổ | G7: 8 | H7: https://voz.vn/p/43907678/ | I7: 2026-10-04 11:09 | J7: Chấp niệm mạnh đấy
A8: 1 | B8: Sẽ sửa thêm nhiều luật để GDP tăng trưởng 2 con số | C8: https://znews.vn/se-sua-them-nhieu-luat-de-gdp-tang-truong-2-con-so-post1686786.html | D8: 7 | E8: 3 | F8: God of Moon | G8: 11 | H8: https://voz.vn/p/43907707/ | I8: 2026-10-04 11:13 | J8: Giờ là tâm ma luôn rồi, chứ chấp niệm gì nữa Được gửi từ myVOZ Next trên iPhone
A9: 1 | B9: Sẽ sửa thêm nhiều luật để GDP tăng trưởng 2 con số | C9: https://znews.vn/se-sua-them-nhieu-luat-de-gdp-tang-truong-2-con-so-post1686786.html | D9: 8 | E9: 3 | F9: cukhai | G9: 12 | H9: https://voz.vn/p/43907709/ | I9: 2026-10-04 11:13 | J9: Chắc không đạt 2 con số thì tâm ma phản phệ, phế hết tu vi thì mới cố tới mức này
A10: 1 | B10: Sẽ sửa thêm nhiều luật để GDP tăng trưởng 2 con số | C10: https://znews.vn/se-sua-them-nhieu-luat-de-gdp-tang-truong-2-con-so-post1686786.html | D10: 9 | E10: 3 | F10: Tô Tặc | G10: 14 | H10: https://voz.vn/p/43907715/ | I10: 2026-10-04 11:14 | J10: Tầm này chỉ đám sân sau với mafia hường hưởng lợi. Hộ kinh doanh với doanh nghiệp vừa và nhỏ xác định chết ngắc.
A11: 1 | B11: Sẽ sửa thêm nhiều luật để GDP tăng trưởng 2 con số | C11: https://znews.vn/se-sua-them-nhieu-luat-de-gdp-tang-truong-2-con-so-post1686786.html | D11: 10 | E11: 3 | F11: clonelandau | G11: 15 | H11: https://voz.vn/p/43907720/ | I11: 2026-10-04 11:14 | J11: Cmx xứng đáng đc dựng nhiều tượng. Tượng cccd, tượng sắp xếp giang sơn, tượng 178, tượng 2 con số, tượng vươn mình …. Thái tổ cũng phải xách dép
A12: 1 | B12: Sẽ sửa thêm nhiều luật để GDP tăng trưởng 2 con số | C12: https://znews.vn/se-sua-them-nhieu-luat-de-gdp-tang-truong-2-con-so-post1686786.html | D12: 11 | E12: 3 | F12: ThangBem2 | G12: 18 | H12: https://voz.vn/p/43907750/ | I12: 2026-10-04 11:19 | J12: Đéo tăng được thì sửa luật để tăng, bố lạy chúng mày.
A13: 1 | B13: Sẽ sửa thêm nhiều luật để GDP tăng trưởng 2 con số | C13: https://znews.vn/se-sua-them-nhieu-luat-de-gdp-tang-truong-2-con-so-post1686786.html | D13: 12 | E13: 3 | F13: blue_heart | G13: 22 | H13: https://voz.vn/p/43907786/ | I13: 2026-10-04 11:24 | J13: Tượng tần cối???
A14: 1 | B14: Sẽ sửa thêm nhiều luật để GDP tăng trưởng 2 con số | C14: https://znews.vn/se-sua-them-nhieu-luat-de-gdp-tang-truong-2-con-so-post1686786.html | D14: 13 | E14: 3 | F14: hoangvu322 | G14: 24 | H14: https://voz.vn/p/43907798/ | I14: 2026-10-04 11:25 | J14: =if(a1>=10,a1,”10%”)
A15: 1 | B15: Sẽ sửa thêm nhiều luật để GDP tăng trưởng 2 con số | C15: https://znews.vn/se-sua-them-nhieu-luat-de-gdp-tang-truong-2-con-so-post1686786.html | D15: 14 | E15: 3 | F15: Raidou | G15: 26 | H15: https://voz.vn/p/43907808/ | I15: 2026-10-04 11:26 | J15: VCL lần đầu tiên nghe tới khái niệm SỬA LUẬT để đạt mục tiêu tăng trưởng trong năm đấy Thôi các bố sửa số luôn đi, muốn bao nhiêu % cứ tự báo với nhau chứ cần gì lằng nhằng vậy
A16: 1 | B16: Sẽ sửa thêm nhiều luật để GDP tăng trưởng 2 con số | C16: https://znews.vn/se-sua-them-nhieu-luat-de-gdp-tang-truong-2-con-so-post1686786.html | D16: 15 | E16: 3 | F16: Bi Beo | G16: 28 | H16: https://voz.vn/p/43907827/ | I16: 2026-10-04 11:30 | J16: ae nào làm nn cấp cao hoặc có người quen làm cấp cao cho hỏi tí...trên đó giờ không ai ý kiến hoặc sợ quá không dám ý kiến cho cmx nữa à ...tham mưu, góp ý, hoạch định thế méo nào, đặt mục tiêu tầm 7-8% so với các nước khác là cũng rất tốt rồi, mà cứ phải vĩ cuồng 2 con số...hay là các bác ấy có tầm nhìn, chiến lược đặc biệt gì, hoặc chỉ thuần đánh bạc liều..
A17: 1 | B17: Sẽ sửa thêm nhiều luật để GDP tăng trưởng 2 con số | C17: https://znews.vn/se-sua-them-nhieu-luat-de-gdp-tang-truong-2-con-so-post1686786.html | D17: 16 | E17: 3 | F17: newmoonZ | G17: 29 | H17: https://voz.vn/p/43907856/ | I17: 2026-10-04 11:33 | J17: Quốc hội chính là dân, dân chốt xong cứ yên tâm nằm im hưởng thụ vì cả hệ thống chính trị vào cuộc phục vụ nhân dân
A18: 1 | B18: Sẽ sửa thêm nhiều luật để GDP tăng trưởng 2 con số | C18: https://znews.vn/se-sua-them-nhieu-luat-de-gdp-tang-truong-2-con-so-post1686786.html | D18: 17 | E18: 3 | F18: Nongdan2017 | G18: 32 | H18: https://voz.vn/p/43907872/ | I18: 2026-10-04 11:35 | J18: Cùng thắc mắc... không biết là đang vì cái gì. Cố để làm chủ công nghệ, cố để có tuyến đường giao thương, cố để tăng số lượng bằng sáng chế..v.v thấy còn có giá trị. Chứ cố để 2 con số, còn éo quan tâm các chỉ số khác thấy sợ vl.
A19: 1 | B19: Sẽ sửa thêm nhiều luật để GDP tăng trưởng 2 con số | C19: https://znews.vn/se-sua-them-nhieu-luat-de-gdp-tang-truong-2-con-so-post1686786.html | D19: 18 | E19: 3 | F19: darkkong | G19: 33 | H19: https://voz.vn/p/43907878/ | I19: 2026-10-04 11:35 | J19: nên nhớ 50 năm qua, từ khi VN độc lập từ 1975 đến giờ, tôi kiểm tra chưa thấy VN năm nào GDP tăng dc 10% cả . Từ khi CMX lên ngôi nắm quyền cái là lập tức ra lệnh cho cấp dưới phải vĩ cuồng tăng GDP phải 10%
A20: 1 | B20: Sẽ sửa thêm nhiều luật để GDP tăng trưởng 2 con số | C20: https://znews.vn/se-sua-them-nhieu-luat-de-gdp-tang-truong-2-con-so-post1686786.html | D20: 19 | E20: 3 | F20: PH007 | G20: 34 | H20: https://voz.vn/p/43907881/ | I20: 2026-10-04 11:35 | J20: Công nhận để thằng bảo vệ, lái xe làm lãnh đạn khác biệt thật, trợn mắt
A21: 1 | B21: Sẽ sửa thêm nhiều luật để GDP tăng trưởng 2 con số | C21: https://znews.vn/se-sua-them-nhieu-luat-de-gdp-tang-truong-2-con-so-post1686786.html | D21: 20 | E21: 3 | F21: Shane64 | G21: 36 | H21: https://voz.vn/p/43907899/ | I21: 2026-10-04 11:38 | J21: 277 ngày 377 nghị định, quá đã, dự kiến cuối năm đạt 500 nghị định
A22: 2 | B22: Giải Jackpot xổ số Mega 6/45 của Vietlott có thể tiến sát đỉnh 159 tỉ đồng | C22: https://tuoitre.vn/giai-jackpot-xo-so-mega-6-45-cua-vietlott-co-the-tien-sat-dinh-159-ti-dong-100260930083548038.htm | D22: 1 | E22: 3 | F22: Kyuckhongten | G22: 2 | H22: https://voz.vn/p/43864969/ | I22: 2026-09-30 11:33 | J22: bịp lót. Biết nó bịp thôi làm 1 con biết đâu trúng (
A23: 2 | B23: Giải Jackpot xổ số Mega 6/45 của Vietlott có thể tiến sát đỉnh 159 tỉ đồng | C23: https://tuoitre.vn/giai-jackpot-xo-so-mega-6-45-cua-vietlott-co-the-tien-sat-dinh-159-ti-dong-100260930083548038.htm | D23: 2 | E23: 3 | F23: sylvie1304 | G23: 4 | H23: https://voz.vn/p/43864998/ | I23: 2026-09-30 11:35 | J23: Biết là bịp nhưng vẫn mơ được trúng số, đổi đời Vì cuộc sống bay giờ quá mệt mỏi vì tiềnnnnnnnnnnnnn
A24: 2 | B24: Giải Jackpot xổ số Mega 6/45 của Vietlott có thể tiến sát đỉnh 159 tỉ đồng | C24: https://tuoitre.vn/giai-jackpot-xo-so-mega-6-45-cua-vietlott-co-the-tien-sat-dinh-159-ti-dong-100260930083548038.htm | D24: 3 | E24: 3 | F24: nguyentungoc0163 | G24: 6 | H24: https://voz.vn/p/43865029/ | I24: 2026-09-30 11:37 | J24: Giả dụ mấy ông trúng thật thì còn tầm hơn 140 tỷ nhỉ, như mấy ông thì mấy ông làm gì Tôi trc nhé, tôi sẽ mua căn nhà trên Lâm Đồng hoặc Đà Lạt ngoài rìa ít dân cư thôi tại tính tôi thích vắng vẻ , trích tầm 1 ít sẽ mua vàng cất trong két sắt rồi mở tiệm tạp hoá bán đồ linh tinh mà sống thôi. Còn lại 100 tỏi chia mỗi Bank 1 ít tiền lời chắc dư sống rồi
A25: 2 | B25: Giải Jackpot xổ số Mega 6/45 của Vietlott có thể tiến sát đỉnh 159 tỉ đồng | C25: https://tuoitre.vn/giai-jackpot-xo-so-mega-6-45-cua-vietlott-co-the-tien-sat-dinh-159-ti-dong-100260930083548038.htm | D25: 4 | E25: 3 | F25: slender.hth | G25: 7 | H25: https://voz.vn/p/43865046/ | I25: 2026-09-30 11:38 | J25: Biết nó bịp đó mà thấy 159 tỏi thơm quá
A26: 2 | B26: Giải Jackpot xổ số Mega 6/45 của Vietlott có thể tiến sát đỉnh 159 tỉ đồng | C26: https://tuoitre.vn/giai-jackpot-xo-so-mega-6-45-cua-vietlott-co-the-tien-sat-dinh-159-ti-dong-100260930083548038.htm | D26: 5 | E26: 3 | F26: zombie6666 | G26: 8 | H26: https://voz.vn/p/43865047/ | I26: 2026-09-30 11:38 | J26: Mua quốc tịch Mẽo cho cả nhà rồi tính tiếp
... A286: 19 | B286: Quyền Linh lên tiếng khi bị nhắc tên giữa vụ án An Cung giả: Khẳng định không liên quan | C286: https://laodong.vn/van-hoa-giai-tri/tung-duong-quyen-linh-hoa-minzy-cung-sao-viet-an-mung-tuyen-viet-nam-vo-dich-1757049.ldo | D286: 20 | E286: 1 | F286: ipodgen2 | G286: 37 | H286: https://voz.vn/p/43820366/ | I286: 2026-09-26 09:27 | J286: Ủa dm hãng nó cung cấp đủ giấy chứng nhận thì nhận job quảng cáo thôi. Chứ ko lẽ phải cầm sản phẩm đi xét nghiệm ah , trách nhiệm của cơ quan chức năng đâu mà đổ lên người quảng cáo

Sheet Bang ngang
A1: Hang | B1: Tieu de | C1: Link bai bao | D1: Link thread | E1: Replies | F1: Tong Ung | G1: Top 1 | H1: Top 2 | I1: Top 3 | J1: Top 4 | K1: Top 5 | L1: Top 6 | M1: Top 7 | N1: Top 8 | O1: Top 9 | P1: Top 10 | Q1: Top 11 | R1: Top 12 | S1: Top 13 | T1: Top 14 | U1: Top 15 | V1: Top 16 | W1: Top 17 | X1: Top 18 | Y1: Top 19 | Z1: Top 20
A2: 1 | B2: Sẽ sửa thêm nhiều luật để GDP tăng trưởng 2 con số | C2: https://znews.vn/se-sua-them-nhieu-luat-de-gdp-tang-truong-2-con-so-post1686786.html | D2: https://voz.vn/t/se-sua-them-nhieu-luat-de-gdp-tang-truong-2-con-so.1285462/ | E2: 139 | F2: 163 | G2: [3 Ung] @Trư Bát Giới͏: Sửa số cho lẹ!!! | H2: [3 Ung] @long020994v3: ể? | I2: [3 Ung] @God of Moon: Công bố GDP 2 con số, ai thắc mắc hay tò mò hỏi thì liên hệ conan phường tư vấn cho, sửa luật làm ccc gì có mệt vậy? Được gửi từ myVOZ Next trên iPhone | J2: [3 Ung] @darkkong: Thực sự rất lo ngại khi xứ này đang dần biến tướng giống Liên Xô 50 năm trước đây, khi mà cấp trên duy ý chí, ra chỉ tiêu tăng trưởng vô lý. Cấp dưới thì sợ hãi bị xử lý nên cố gắng làm giả tạo mọi số liệu để lấy lòng cấp trên. Hậu quả thật khủng khiếp, những năm 1980, Liên Xô với diện tích rộng 22 triệu km2, chiếm 1/6 diện tích Trái Đất, rộng lớn đến bao la bát ngát trải dài tới tận 2 bờ Đại dương, chim bay mỏi rã cánh, rơi xuống đất chết vì kiệt sức mà còn chưa bay hết 1/10 chiều dài lãnh thổ Liên Xô. Sở hữu diện tích đất nông nghiệp lớn nhất thế giới, đất canh tác trồng trọt rộng hơn các quốc gia khác cả trăm lần , v ậy mà sau mới lòi ra là thiếu lương thực, phải nhập khẩu lương thực từ các nước khác về thì mới đủ ăn mặc dù dân số Liên Xô ko lớn. Dân số Liên Xô hồi đó t 170tr dân, còn chưa bằng dân số Bangladesh hiện nay. Cái nhục nhã nhất là quan chức LX phải đi n… | K2: [3 Ung] @auster: Hầy | L2: [3 Ung] @Ông Tổ: Chấp niệm mạnh đấy | M2: [3 Ung] @God of Moon: Giờ là tâm ma luôn rồi, chứ chấp niệm gì nữa Được gửi từ myVOZ Next trên iPhone | N2: [3 Ung] @cukhai: Chắc không đạt 2 con số thì tâm ma phản phệ, phế hết tu vi thì mới cố tới mức này | O2: [3 Ung] @Tô Tặc: Tầm này chỉ đám sân sau với mafia hường hưởng lợi. Hộ kinh doanh với doanh nghiệp vừa và nhỏ xác định chết ngắc. | P2: [3 Ung] @clonelandau: Cmx xứng đáng đc dựng nhiều tượng. Tượng cccd, tượng sắp xếp giang sơn, tượng 178, tượng 2 con số, tượng vươn mình …. Thái tổ cũng phải xách dép | Q2: [3 Ung] @ThangBem2: Đéo tăng được thì sửa luật để tăng, bố lạy chúng mày. | R2: [3 Ung] @blue_heart: Tượng tần cối??? | S2: [3 Ung] @hoangvu322: =if(a1>=10,a1,”10%”) | T2: [3 Ung] @Raidou: VCL lần đầu tiên nghe tới khái niệm SỬA LUẬT để đạt mục tiêu tăng trưởng trong năm đấy Thôi các bố sửa số luôn đi, muốn bao nhiêu % cứ tự báo với nhau chứ cần gì lằng nhằng vậy | U2: [3 Ung] @Bi Beo: ae nào làm nn cấp cao hoặc có người quen làm cấp cao cho hỏi tí...trên đó giờ không ai ý kiến hoặc sợ quá không dám ý kiến cho cmx nữa à ...tham mưu, góp ý, hoạch định thế méo nào, đặt mục tiêu tầm 7-8% so với các nước khác là cũng rất tốt rồi, mà cứ phải vĩ cuồng 2 con số...hay là các bác ấy có tầm nhìn, chiến lược đặc biệt gì, hoặc chỉ thuần đánh bạc liều.. | V2: [3 Ung] @newmoonZ: Quốc hội chính là dân, dân chốt xong cứ yên tâm nằm im hưởng thụ vì cả hệ thống chính trị vào cuộc phục vụ nhân dân | W2: [3 Ung] @Nongdan2017: Cùng thắc mắc... không biết là đang vì cái gì. Cố để làm chủ công nghệ, cố để có tuyến đường giao thương, cố để tăng số lượng bằng sáng chế..v.v thấy còn có giá trị. Chứ cố để 2 con số, còn éo quan tâm các chỉ số khác thấy sợ vl. | X2: [3 Ung] @darkkong: nên nhớ 50 năm qua, từ khi VN độc lập từ 1975 đến giờ, tôi kiểm tra chưa thấy VN năm nào GDP tăng dc 10% cả . Từ khi CMX lên ngôi nắm quyền cái là lập tức ra lệnh cho cấp dưới phải vĩ cuồng tăng GDP phải 10% | Y2: [3 Ung] @PH007: Công nhận để thằng bảo vệ, lái xe làm lãnh đạn khác biệt thật, trợn mắt | Z2: [3 Ung] @Shane64: 277 ngày 377 nghị định, quá đã, dự kiến cuối năm đạt 500 nghị định
A3: 2 | B3: Giải Jackpot xổ số Mega 6/45 của Vietlott có thể tiến sát đỉnh 159 tỉ đồng | C3: https://tuoitre.vn/giai-jackpot-xo-so-mega-6-45-cua-vietlott-co-the-tien-sat-dinh-159-ti-dong-100260930083548038.htm | D3: https://voz.vn/t/giai-jackpot-xo-so-mega-6-45-cua-vietlott-co-the-tien-sat-dinh-159-ti-dong.1284286/ | E3: 655 | F3: 330 | G3: [3 Ung] @Kyuckhongten: bịp lót. Biết nó bịp thôi làm 1 con biết đâu trúng ( | H3: [3 Ung] @sylvie1304: Biết là bịp nhưng vẫn mơ được trúng số, đổi đời Vì cuộc sống bay giờ quá mệt mỏi vì tiềnnnnnnnnnnnnn | I3: [3 Ung] @nguyentungoc0163: Giả dụ mấy ông trúng thật thì còn tầm hơn 140 tỷ nhỉ, như mấy ông thì mấy ông làm gì Tôi trc nhé, tôi sẽ mua căn nhà trên Lâm Đồng hoặc Đà Lạt ngoài rìa ít dân cư thôi tại tính tôi thích vắng vẻ , trích tầm 1 ít sẽ mua vàng cất trong két sắt rồi mở tiệm tạp hoá bán đồ linh tinh mà sống thôi. Còn lại 100 tỏi chia mỗi Bank 1 ít tiền lời chắc dư sống rồi | J3: [3 Ung] @slender.hth: Biết nó bịp đó mà thấy 159 tỏi thơm quá | K3: [3 Ung] @zombie6666: Mua quốc tịch Mẽo cho cả nhà rồi tính tiếp | L3: [3 Ung] @Tsganey: các bác cẩn thận kẻo bị seeder dụ kèo tỉ lệ trúng của 6/45 là 1 / 8.145.060 thì có cức mà trúng nổi | M3: [3 Ung] @slender.hth: 140 tỷ thì tôi sẽ lấy 10 tỷ cất một căn nhà có chỗ chui ra chui vào, 10 tỷ chia cho bà con họ hàng thân quen trong nhà. Còn lại 130 tỷ tôi sẽ đem làm từ thiện, giúp đỡ các hoàn cảnh khó khăn. Đang giả dụ nên tôi xạo chó đó, chứ tôi mà trúng thật thì đến má tôi còn không biết | N3: [3 Ung] @nghiaagv: mua 2 vé là chia 2 tỉ lệ trên, 10 vé là chia 10 rồi. | O3: [3 Ung] @Mr Tuna: Theo lý thuyết bao đủ bộ số là gần 82 tỷ thôi. Ae nào có 82 tỷ mạnh dạn đi, bú x2 là dễ. Tôi chỉ lo khi bao đủ hết thì tự dưng có 4 người cùng trúng jackpot thôi. | P3: [3 Ung] @klc8855: Mega 150 tỏi, Power cũng gần 100 tỏi. Mình muốn ngày trước trúng Mega, ngày sau trúng Power. Mình có tham lam quá ko ? | Q3: [3 Ung] @RaitoYg: 159 tỏi thì cái đầu tiên tôi sẽ mua đó là tịch Mẽo | R3: [3 Ung] @Mr Tuna: Giả sử bạn bỏ ra 81 tỷ mua tất cả bộ số. Xác suất trúng Jackpot là 100%, cộng thêm các giải phụ. Hiện đang 159 tỷ, cứ cho là bạn mua 81 tỷ còn ae khác mua 20 tỷ đi, vietlot trích ra 55% cho vào jackpot thì jackpot nổ là thêm 55 tỷ nữa, tổng là 214 tỷ. Bây giờ cùng tính số tiền thu được nào: Tổng tất cả giải nhất nhì ba sẽ là 11 tỷ Jackpot sẽ là 214 tỷ nếu 1 mình bạn trúng, 107 tỷ nếu có 2 người, khoảng 70 tỷ nếu có 3 người. 2 trường hợp đầu là bạn lãi chắc chắn sau khi đã trừ thuế. Trường hợp thứ 3 là bạn lỗ tiền thuế TNCN. Còn từ 4 người thì móm nặng | S3: [3 Ung] @YamL: 6-45 và 6-55 hai kỳ quay liên tiếp ra số giống nhau, vcl tụi nó bịp công khai luôn chứ chẳng giấu diếm gì nữa, anh nào tính xác suất 2 ngày liên tiếp ra được bộ 3 số đầu giống nhau như này là bao nhiêu phần trăm không nhỉ | T3: [3 Ung] @Ngoc.Trinh: Tin tưởng và đồng hành | U3: [3 Ung] @trivu11: Ngày mai mà các fen mà thấy tôi lên mạng nói đạo lý là biết giải thưởng thuộc về ai rồi | V3: [3 Ung] @Cơn Mê Bất Tận: Trúng dẫn múi mích lên bờ xuống biển | W3: [3 Ung] @leviet51xf: Chiều về làm 5 vé, trúng thì lên voz nổ stk cho 200 vozer đầu tiên like cmt này mỗi người 5 triệu | X3: [3 Ung] @malacat: Giờ mà trúng 140 tỉ thì mua: 1 căn nhà to có chỗ đậu xe hơi at tphcm mua 1 car chừng 2-3 tỷ thôi -mua dãy nhà trọ cho thuê lấy tiền hàng tháng ngay khi trúng 140t thì book vé máy bay ✈ra hanoi du lịch 1 tuần dành ra 10ty gửi bank lấy lãi còn lại mua gold,gửi bank,mở 1 tiệm tạp hóa Trúng 140 tỷ rồi thì có dư time đi học lấy drive license xe hơi | Y3: [3 Ung] @CrazyLove00: Lỗ 20k | Z3: [3 Ung] @selenia15: Trúng được 140 thì chi ra 16-20 tỷ mua nhà vườn 7000m2 đang rao rầm rộ trên đắc lắc. Còn đâu bỏ hết vào ngân hàng lấy lãi. Số tiền lãi hàng tháng ăn chơi du lịch khắp thế giới luôn. Có nấy tiền còn đi lao vào kinh doanh tạp hóa với nhà trọ, không may dính vụ cháy chết người , hay kê khai thuế sai thì lại mất cả mớ tiền. Đúng tư duy bần nông, có tiền mà cũng không biết cách làm cho mình sướng.
A4: 3 | B4: [Dịch]Tàu thuyền xếp hàng chờ tiếp nhiên liệu tại cảng lớn nhất Trung quốc khi nguồn cung dầu bị siết chặt. Giá dầu ở đây đã cao hơn Singapore 25% | C4: https://www.bloomberg.com/news/articles/2026-09-30/ships-face-fuel-delays-at-china-s-zhoushan-on-supply-squeeze | D4: https://voz.vn/t/dich-tau-thuyen-xep-hang-cho-tiep-nhien-lieu-tai-cang-lon-nhat-trung-quoc-khi-nguon-cung-dau-bi-siet-chat-gia-dau-o-day-da-cao-hon-singapore-25.1285464/ | E4: 68 | F4: 68 | G4: [3 Ung] @ghostlab: Đắt hơn những 25% lại thêm quả xếp hàng cả tuần thế kia thì thà chạy xuống Singapore nạp cho lành | H4: [3 Ung] @BlueHills: Thôi chịu khó qua Mạc Tư Khoa quỳ Putin mở thêm van dầu đi, bữa qua deal mà đòi nó giá khí đốt bằng trong nước nó, nó dỗi nó bỏ về | I4: [3 Ung] @boyhandsome: Thì cái cảng "nhộn nhịp nhất thế giới" này sẽ tan hoang chứ sao nữa fen. Anh police của thế giới đánh cờ vây kinh dị thật. | J4: [3 Ung] @ohmarion: TQ mà đi mua dầu thế giới là sml hết. Chuẩn bị đi | K4: [3 Ung] @ohmarion: Nói chuyện với mấy thằng cãi cùn thiếu não phát mệt. Thằng Tàu bị gì thì keme nó. Tạo đang lo cho thân tao trước thôi, xăng sắp lên 30k rồi | L4: [3 Ung] @boyhandsome: Cóa xài được éo nữa đâu. Venezulla thì bị Mỹ tóm. Iran thì bị Mẽo chặn đường Hormuz, đường biển Đỏ thì bị Houthi nó chặn. Tàu cẩu đang tính đi đường Bắc Cực thì mới tính thôi Mẽo nó tóm mẹ nó Greenland, đặt 3 căn cứ quân sự. | M4: [3 Ung] @Sầu đời: Có mày dốt ấy. Có nghĩa là nó cạn mẹ nó dầu dự trữ. Cũng có nghĩa là nguồn nhập dầu của nó không đủ chứ sao nữa. Một đất nước trùm culi sản xuất, đéo có dầu thô để làm ra nguyên liệu nhựa, hóa chất thì chết mọe cả 3 lò nhà tàu cẩu luôn ấy. | N4: [3 Ung] @Chủ Tiệm: Thật sự là không hiểu mày hả hê gì khi nó hết dầu? Phận đáy xã hội, sầu đời, muốn reset để ngoi lên à? Giả sử nó hết dầu thật thì những thằng nhỏ khác còn gì? Chắc còn bộ xương khô. Nhưng mà tin buồn là nó del bao giờ hết dầu, nó còn nhiều dầu vãi ra. Nó kéo đi nhập khẩu là như tao giải thích (mà có giải thích chắc del gì mày hiểu), là nó sắp cấm xuất khẩu nhiên liệu. Lúc đó thì VN và các nước ĐNA banh xác nhé. https://www.economist.com/finance-and-economics/2026/08/09/china-is-now-the-worlds-great-oil-power | O4: [3 Ung] @Sầu đời: Thôi mày im mẹ nó mõm đi. Mày khóc thương cho tàu cẩu bị nát bét thì đó là việc của mày. Việc đéo gì tao phải khóc thương cho việc tàu cẩu nát hả thằng đần? Nói chuyện như con bò. | P4: [3 Ung] @NightStaker: Thế giới này có chỗ nào ưa tàu cẩu kô fen? | Q4: [3 Ung] @Namvu040386: Giống hán khựa chuột bọ này xứng đáng bị mọi người khắp thế giới tru diệt. Chú mài nói những điều ko liên quan để đánh lạc hướng à. Một dân tộc mạt hạng hèn hạ | R4: [2 Ung] @secret004: Thế mới thấy chính phủ việt nam giỏi thế nào, giá xăng dầu việt nam rẻ hơn ở trung quốc nhiều | S4: [2 Ung] @ohmarion: Thì hiện tại do nó xài xăng của Ngố nên thế giới mới có đủ xăng mà xài đó. | T4: [2 Ung] @baolong345: K ai nhắc tới mình cả, phải kể thêm chi vậy? | U4: [2 Ung] @nick thứ bao nhiêu rồi: Nga có xuất xăng đâu mà nói gì kì quái vậy? Giá xăng của Tàu cao vì các teapots của Tàu không thể nhập dầu Iran và dầu Vene giá rẻ nữa. | V4: [2 Ung] @uocmovietlot: bóp cỡ nào thì kinh tế Tây Nam anh trung béo không bao giờ chết được Còn Sin thì muôn đời, trừ khi Thái dúi làm kênh Kra chứ thuyền kiểu đóe gì chả đi qua chỗ nó Cái t đang nói là đáp ứng nhu cầu xăng dầu cho 6tr dân khác với 10tr dân | W4: [2 Ung] @Chủ Tiệm: Thằng lều báo viết láo, thêm mấy thằng lều bạn đọc dốt. Giá dầu tăng cao là do nó gom hàng liên tục trước tin Tàu chuẩn bị cấm xuất khẩu xăng dầu thành phẩm cho khu vực Châu Á TBD https://www.reuters.com/business/energy/oil-prices-barely-changed-investors-assess-us-iran-peace-talks-gulf-exports-2026-10-01/ Cũng có tin đồn là Mỹ cũng chuẩn bị cấm xuất khẩu diesel để kìm giá trong nước. Điều này ảnh hưởng nặng nề nhất chắc chắc là khu vực ĐNA và VN. Đợi tới mà đụng được tới cái ngón chân của Bình hí thì VN khủng hoảng mẹ rồi. Vậy mà có nhiều thằng vẫn ngồi đó hả hê. Giả sử xã hội này có khó khăn cỡ nào thì những thành phần đáy xã hội như tụi bây cũng không khá hơn đâu, nói thật. | X4: [2 Ung] @Chủ Tiệm: Tao nói quá đúng còn gì nữa, phận sầu đời đáy xã hội mở miệng chỉ biết chửi thôi, nãy giờ tao nói gì chắc mày cũng không hiểu đâu,. Cứ việc chửi đi nếu mày cảm thấy thoải mái | Y4: [2 Ung] @Chủ Tiệm: Xăng mình là ron95 pha thêm 10% sinh học, chưa kể bỏ hết thuế phí, đừng tưởng bở. Thằng xăng sinh học này xài hao hơn 95 nhiều. | Z4: [2 Ung] @mouse123479: Ợ. Mà nói gì thì nói cũng mong Tàu sụm nụ lẹ, hoặc ngày mai luôn cũng đc. Chứ có thằng mỗi ngày hao tinh tốn lực tạo ra mấy chục cái clone sục chéo. Dù gì vozer cũng toàn u30 u40. Mỗi ngày sụt 1 cái là phải mất 2 ngày hồi phục rồi. Kaka.
A5: 4 | B5: Mazda CX-5 lại giảm giá, có đại lý chào bán từ 638 triệu đồng | C5: https://dantri.com.vn/o-to-xe-may/mazda-cx-5-lai-giam-gia-co-dai-ly-chao-ban-tu-638-trieu-dong-20261003181844153.htm | D5: https://voz.vn/t/mazda-cx-5-lai-giam-gia-co-dai-ly-chao-ban-tu-638-trieu-dong.1285416/ | E5: 87 | F5: 68 | G5: [3 Ung] @Mr Tuna: 2020 bán 200 củ bạn ơi | H5: [3 Ung] @zxcvbnm25251325: Cố tý lấy Cross hybrid ngon hơn | I5: [3 Ung] @zzkaka: Cố tý là bao nhiêu, ngáo ngơ đừng cmt nữa. | J5: [3 Ung] @namanhgroup: ai đi nhiều khuyên thật mua xe điện cho nó tiết kiệm, sau này bảo dưỡng nó cũng đơn giản hãng gì cũng dc. Còn ai ít đi mua về lâu lâu đi chuyến thì hẵng mua xe xăng. | K5: [3 Ung] @ctw_god: cx5 ra bản mới k biết thaco có giữ bản này k? giá êm quá, làm mấy con khác áp lực cũng giảm theo. 5c thì cx5 7c có destinator giá quá êm via theNEXTvoz for iPhone | L5: [3 Ung] @prochang12: Theo các “chiên” gia ngành xe dự đoán thì bản mới sẽ tầm 1 tỏi, bản cũ này bán song song cùng bản mới. Tôi cũng nghĩ vậy là hợp lý. Bản cũ vẫn quá hay, đa số vẫn thích phím vật lý và ko cần màn to đùng như bản mới. Vẫn duy trì bán bản cũ và giảm giá tiếp thì những hãng khác ra chuồng gà hết. | M5: [3 Ung] @ctw_god: thím 2 tự trả lời rồi đó 2 phân khúc khác nhau mà, cũng giống như cách Apple bán hàng, ra bản mới vẫn bán bản cũ song song với giá thấp hơn cho người dùng dễ tiếp cận via theNEXTvoz for iPhone | N5: [3 Ung] @bboyz269: Mua năm 2024 bản pre 820 (được giảm 10 củ) nay có 750. Giá new vậy giờ bán lại chắc chỉ được 650. Ông nào mua năm 2025 chắc còn khóc hơn nữa | O5: [3 Ung] @Bảo vệ 15 năm: Cố tý cố tý cuối cùng cố 1 tý lên thẳng Maybach S680 đi cho sướng | P5: [3 Ung] @h.a.d: mua 2022 bản pre giá 920, dc giảm còn 890 đây, lăn bánh xong tròn tỏi, mới đi dc 26k km giờ bán 600 éo nổi via theNEXTvoz for iPhone | Q5: [3 Ung] @pebuon69: Vẫn lùa được gà thôi, bán được 1 con thì đóng cửa cả tháng vẫn lãi. Đa phần là đám cờ bạc, lô đề,... chúng nó kiếm chác được nên chẳng nghĩ nhiều, xe mới thì k đợi dc vì biết đâu mai lại sạch tài khoản nên mua con cũ cho lẹ. Chứ người thường, tiết kiệm mãi mới đc ít tiền, chả ai ngu đâm đầu vào mấy con xe cũ cả. Như tôi đi xem xe, tôi phải gọi cho cả chục cái showroom, đại lý check giá, rồi tham khảo qua thị trường xe cũ nữa. Của một đống tiền, sao vội được | R5: [3 Ung] @Con hổ yêu: Chắc anh dính vô chơi bời gì chứ sống độc thân mà 30tr mỗi tháng ko để dc 10-15tr thì phải tự trách anh k biết quản lý tiền thôi. | S5: [2 Ung] @guess123: Cố nửa chiếc xe chứ mấy )) via theNEXTvoz for iPhone | T5: [2 Ung] @kangta4ever: Đkm nó cứ giảm giá là lại thèm, mà mua thì phí. Cay vl via theNEXTvoz for iPhone | U5: [2 Ung] @anhtien1292: Des rộng rãi 7c nhưng máy yếu. Cross chật hơi bí nhưng máy 1.8 khá mạnh cho cái xác xe đó (ko tính hev) | V5: [2 Ung] @crv2018: Giờ cầm 500t ra kiếm xe lướt xe mới tha hồ lựa, móa có 4 cây hà, nhớ thời mua chiếc dream 7 số tận gần 10 cây vàng | W5: [1 Ung] @toxic_guy: Con này vẫn quá ngon trong tầm giá. Thiết kế ko lỗi thời nữa. via theNEXTvoz for iPhone | X5: [1 Ung] @xiaoloz: này thì đội xe cũ ôm những chiếc cx5 2020 2024 khóc cạn nước mắt | Y5: [1 Ung] @dung hong kia nick tao: con em họ mới mua con toyota gì như củ đậu hết 450 củ kêu nó đợi tết đi có xe giãm mua mà ko chịu gấp làm cm gì , cho nó vay 200 mua con cx5 này chạy cho sướng mà méo chịu , con con toy chật bm , méo có máy lạnh ghế sau , cái màn màn thì bé tí teo. via theNEXTvoz for iPhone | Z5: [1 Ung] @Ti Amo: con này đc cái dáng, máy, phổ thông, nhiều đồ thay sẵn còn lại trung bình.
A6: 5 | B6: GDP quý IV phải tăng trên 12,5% để đạt mục tiêu tăng trưởng hai con số | C6: https://vneconomy.vn/gdp-quy-iv-phai-tang-tren-125-de-dat-muc-tieu-tang-truong-hai-con-so.htm | D6: https://voz.vn/t/gdp-quy-iv-phai-tang-tren-12-5-de-dat-muc-tieu-tang-truong-hai-con-so.1285317/ | E6: 97 | F6: 127 | G6: [3 Ung] @mr.huster: S ba vì mới xúc nhà rồi, mở thêm cái V tam đảo, hoặc lên dãy trường sơn phân lô luôn thì lên 12.5 là dễ via theNEXTvoz for iPhone | H6: [3 Ung] @ForFreedom: Cái bavi ko tiếc bằng đèo hải vân. Thà nó làm khách sạn thiên nhiên. Xây ko phá rừng thì ok Đàng này nó phạt banh cả đồi luôn. Đúng lũ hút máu | I6: [3 Ung] @Sườn xào chua ngọt: Lại thúc các thể loại tín dụng cho v+s và đầu tư công rồi. Không biết từ đây đến cuối năm phải thêm bao nhiêu nơi căng băng rôn đỏ, thức đêm canh gác để được 2 chữ số | J6: [3 Ung] @chiro: có cái view đi tàu ngắm cho đẹp. Kết nối du lịch Huế ĐN thì nó đem san bằng hết. Rồi chuẩn bị xây lên rừng bê tông. Nói tới cái nguỵ biện là không phá rừng, toàn là cây bụi cây thấp. Thiên nhiên vừa mới hồi sinh, chưa kịp lớn nó cào hết còn nguỵ biện. H tàu Huế Đn, phía đn chã còn vẹo j để ngắm nữa. via theNEXTvoz for iPhone | K6: [3 Ung] @Toler111: 2 năm nay các vụ cướp đất ở Hà Nội và các tỉnh miền bắc diễn ra tần suất dày đặc và quy mô lớn. Nhưng càng như vậy thì lại càng sinh ra thế hệ bò đỏ mới càng mù quáng, đây đúng là nghịch lý rất khó hiểu | L6: [3 Ung] @AltaIr21: ngắm cảnh có ra đc quốc tịch, bò dát gold, nhà cửa biệt thự bên tư bản ko??? | M6: [3 Ung] @net37online: Có tăng thực không cứ thành tích thế này bên dưới lại cứ biến báo con số thôi. | N6: [3 Ung] @Hôi Phát Lão Giả: Dân vẫn còn tin yêu cảng và nhà nghỉ lắm Ngu dốt như vậy thì còn khổ dài | O6: [3 Ung] @Make Y.Maga Great Again: Thiên tày kĩ trị nói r đấy Phải bùa cho đc cho tau | P6: [3 Ung] @Neverwhere: Ngược lại, chẳng có gì khó hiểu cả. Đấy là phản ứng sinh tồn của một số người trước sự hung bạo, và khi nhìn những người ấy, tôi chỉ thấy nỗi khiếp sợ và sự thần phục. Anh càng bạo ngược, sắt máu thì càng có nhiều kẻ sẵn sàng làm mọi thứ, nói bất kể điều gì để chứng tỏ sự trung thành, mẫn cán và làm hài lòng anh, thế thôi. | Q6: [3 Ung] @Dr Lê Thẩm Dương: Chúng ta chưa có tòa nhà cao nhất thế giới, chưa có cây cầu dài nhất thế giới, chưa có đường sắt tốc độ cao dài nhất thế giới, chưa có kênh đào lớn nhất thế giới... còn nhiều thứ phải phấn đấu lắm fen | R6: [3 Ung] @10x3: Cái làng Vân thật sự quá đáng tiếc, chưa kể thiên nhiên, cái di tích Nam Chơn với Chơn Sảng cũng dính vào dự án này; phục dựng hoặc ít nhất bảo tồn nguyên vẹn thì cùng với Hải Vân quan + tường lũy Quảng Ngãi dư sức đủ làm cái di sản unesco để hút du lịch lâu dài Nhưng mấy con chó ngu thích tiền tươi hơn | S6: [3 Ung] @StampZZ2: Thì dân người ta biết cả, chẳng qua là không dám/không thể lên tiếng. Nói ra cũng có thay đổi được gì đâu, lại còn bị chúng nó đập. Giờ cách phản kháng ôn hòa nhất là nằm thẳng, éo lập gia đình, đẻ đái gì nữa. Tiền làm ra bao nhiêu xài bấy nhiêu. Còn anh nào đủ khả năng thì thoát đi sớm sang xứ giãy chết, ít ra còn có thêm cơ hội. | T6: [3 Ung] @StampZZ2: Anh phải lên Cát Bà xem bọn Sun chúng nó phá tan tành cả cái vịnh trước chục đường chính thị trấn. Giờ vẫn lèo tèo không bán được, du lịch thì thiệt hại nặng nề - bọn nước ngoài đâu có trả tiền để tham quan 1 cái đại công trường toàn bê tông, còn chặt chém khách trong nước thì được bao nhiêu đồng; nói chung bà con đói mốc mồm cả ra. Tôi từng có thời gian sống và làm việc trên Cát Bà, mấy người tôi quen trên đảo giờ chửi bọn Sun như chó vì giờ chả biết làm gì để kiếm ăn khi mà du lịch gần như phế hẳn. Thế mà với bọn súc vật đấy vẫn là chưa đủ đâu. Nghe đồn là chúng nó đang nhăm nhe thêm vài chỗ nữa trên đảo. | U6: [3 Ung] @giayasics: mấy thằng trang đỏ còn khiêu khích gen z nào phản ứng ra chúng nó đấm vỡ mồm | V6: [3 Ung] @StampZZ2: Sau vụ gốc cây tôi nghĩ tụi gen z cũng sáng mắt sáng lòng ra rồi. Nếu như không thể lên tiếng hoặc bắt tay vào làm cái gì đó để thay đổi thời cuộc thì chi bằng cứ kệ con mịe nó đi cho chúng nó chết hẳn. | W6: [3 Ung] @shakaxunu5: ôi dào số của mấy bố, mấy bố thích cook kiểu đéo nào chả dc quan trong dân có tiền thêm ko, có bớt chạy grab kiếm cơm từng ngày ko 1 lũ bùa số liệu hùa theo thằng chế mặt xọ đúng ngàn năm tăm tối | X6: [3 Ung] @.Unlimited.50: Tại sao không xuất ngoại rồi chi tiêu bên đó, 1 đồng cà thẻ ngoại tệ là 1 đồng vn thiếu hụt Thay vì đi phú quốc, có thể đi thái, mã (tụi trẻ đang hướng đi mã vì rẻ + hiện đại) | Y6: [3 Ung] @The Muad'dib: Con số đó là cái cớ cực đẹp để đẩy mạnh đầu tư công và plbn thôi. Do lên ngôi k chính danh nên phải tung ra các miếng mồi để an lòng các bên. | Z6: [3 Ung] @awsvps1: Giỏi vkl, thèn nào cũng yêu cầu xong này xong kia còn làm như nào thì đóe thấy thèn nào nói =]] Và nếu k dc thì thèn nào chịu trách nhiệm, vô tù chẳng hạn
A7: 6 | B7: [Dịch]Kinh tế suy yếu, bầu không khí u uất bao trùm khiến người dân Trung quốc đầy áp lực và bắt đầu trút giận lên nhau | C7: https://www.nytimes.com/2026/10/02/opinion/china-anger-economic-frustration.html | D7: https://voz.vn/t/dich-kinh-te-suy-yeu-bau-khong-khi-u-uat-bao-trum-khien-nguoi-dan-trung-quoc-day-ap-luc-va-bat-dau-trut-gian-len-nhau.1285399/ | E7: 81 | F7: 101 | G7: [3 Ung] @BlueHills: Trong các cuộc chiến đẫm máu nhất nhân loại thì các cuộc nội chiến TQ luôn nằm top, Thái Bình Thiên Quốc là 1 ví dụ | H7: [3 Ung] @HAM GAI: Đi tàu về mới thấy mấy năm gần đây dân nó u ám thật sự. | I7: [3 Ung] @fearless1: [Dịch]Kinh tế suy yếu, bầu không khí u uất bao trùm khiến người dân Trung quốc đầy áp lực và bắt đầu trút giận lên nhau ​ | J7: [3 Ung] @NamekchạyExciter: Chả trách mà các thể loại cẩu nô tài toàn vào vozer xong chửi nhặng lên, rồi phải sóc mấy cái tào lao nhảm nhỉ như chuyện Mỹ sa lầy ở Iran, lính Mỹ quỳ trải thảm rồi chuyện Chúm Tro đón Tập ở sân bay, rồi đến độ phải tuyệt vọng đi đặt điều kinh tế Mỹ nát như cháu chó. Hóa ra là do tuyệt vọng vì bố chúng nó đang nát | K7: [3 Ung] @HideHa2: Thật luôn, thấy thằng dư luận viên tàu cẩu long march (trường chinh) ngày ngày cần mẫn lên bài sóc lọ cẩu mà thấy thảm vcl. Đéo hiểu sao chúng nó nát như cứt nhưng cứ phải sóc lọ cẩu ở Việt Nam làm mẹ gì không biết. | L7: [3 Ung] @mouse123479: Năm nay kinh tế ngoài Mỹ thì nước nào chả tệ. Thằng Tàu là nước xuất siêu thì chả thế. Cơ mà báo phương Tây viết về Tàu thì Tàu buồn 7 thì nó viết 8 9 10. Vậy thôi. Nhưng buồn vẫn là buồn. | M7: [3 Ung] @neroj1: Chắc chắn là uy tín gấp ngàn lần mấy báo tàu cẩu ca ngợi thành tựu rực rỡ của chủ tẹch Tẹp Cẹn Bình rồi : | N7: [3 Ung] @ZeonMask: "Opinion", anh cứ hiểu nó ngang ngửa mấy bài "tâm sự" đăng trên báo VN ấy | O7: [3 Ung] @Cau Khenh: Tuổi lol, nói thế cho nhanh và vuông. Tập cẩu éo bao giơ có cái dũng khí của Putin. Đến Đài Loan , Phillipine nó còn cho tàu hải cảnh đuổi thuyền bè của tàu cẩu chạy như vịt. | P7: [3 Ung] @hoanglong0712: Đúng rồi , cty còn ở trên đất khựa là bị thuế mẽo đấm | Q7: [3 Ung] @tv film: Mỹ nó đánh thuế và cấm đồ tàu xuất sang mỹ. Phải qua vn mở nhà máy để làm made in vn mà xuất qua chứ. Ở lại thì toàn bộ chết, qua đây thì thằng chủ sống lôi vài thèn đệ + chuyển lãi về lại trung quốc thông qua giá mua nvl cao via theNEXTvoz for iPhone | R7: [3 Ung] @claudio.caniggia: Tôi nhắc anh 1979, 1000 năm.... Đừng bao giờ coi thường thằng mạnh hơn mình dù nó có hèn hạ thế nào. | S7: [3 Ung] @thefirerises: Thì hậu quả của việc dân Tàu mâu thuẫn nhau cũng là do mấy cái chính sách từ chục năm trước rồi, và cũng nói chán chê: Chính sách 1 con suốt hơn 30 năm phá nát truyền thống gia tộc, biến đạo hiếu thành giao dịch. Phổ cập đại học cho lắm, rồi thị trường không đáp ứng được số việc làm tương ứng. Làm đến 35 tuối bị coi là người thừa, dễ thay thế. Sản xuất thì bất chấp cung cầu, spam hàng giá rẻ đá chén cơm của các nước khác, khiến bọn nó phải hạn chế hàng của Tàu, thành ra bọn nó phải trữ một lượng hàng thừa mà người trong nước không có nhu cầu dùng, gây thêm áp lực cho chính người lao động trong nước. Theo "quy luật" thì đàn ông thích cưới phụ nữ trẻ, còn phụ nữ thích lấy đàn ông giá trị cao hơn, vì thế mà đàn ông trước phải chuẩn bị sính lễ theo truyền thống, giờ đây phải có thêm nhà, thêm xe, cái mà chỉ có tỉ lệ rất ít đảm bảo được. Thành ra đàn ông nông thôn thì … | T7: [3 Ung] @nonamedmm: Hèn chi dạo này xuất hiện mấy thằng cay cú gay gắt trong vozer nhiều vô kể, một câu chúm tro 2 câu chúm tro rồi thêm cả đống mặt cười, ngôn từ thì cay cú, loạn hết cả lên | U7: [3 Ung] @zFlyWithMe: 1 2 năm nữa thì khéo VN cũng éo khác gì. Cái tôi của thằng CMX cao quá, coi dân như rơm rác mẹ rồi. | V7: [3 Ung] @chipkoi002: Sau covid 2020 thì khi cả thế giới đang bị vật lộn bởi con covid thiếu hàng hoá thì tàu nó đem con bài hàng gia rẻ ra để lôi kéo trừng phạt các nước không theo nó, kiểu như nó cấm biên VN. Lúc đó thế giới đang vật lộn với covid nên chưa làm gì được nó. Lúc đó cẩu nô lại chả lên sục là càng nâng thuế thì dân mỹ càng phải mua đồ giá đắt… nhưng sau covid thì thế giới thấy nếu bỏ trứng vào 1 giỏ rất nguy hiểm, nhất là 1 nước tham vọng như TQ. Nếu nó lại dùng con bài hàng giá rẻ + cấm XK thì nền kinh tế nước khác theo không kịp. Nên mới có sự chuyển dịch từ 2022 cho tới nay. 5 năm qua thì các công ty FDI nó đã rời sang ấn ** + asean để tránh lỡ sau này lại có 1 cái covid thứ 2 TQ nó lại dùng chiêu trò bán hàng giá rẻ để mặc cả. Đương nhiên TQ cũng là nước có thực lực thì bọn phương tây nó phải đập từ từ và có chiến lược chứ k phải kiểu cuba mà thích cái là đập ngay. Cái … | W7: [3 Ung] @Yolo22_3: Sau nhiều năm tôi nhận ra tàu cẩu và cái chế độ của nó dậm chân tại chỗ thôi, không thể phát triển như Mỹ. Vấn đề là gì ? là nó chính trị hóa hệ thống công quyền triệt để, biến một công chức có thể thăng tiến nhờ thành tích chính trị (luôn muốn an toàn, chọn những thứ chung chung, dễ làm dễ thấy, khẩu hiệu hoành tráng, đao to búa lớn), thay vì tạo ra những cải cách đột phá vì nhu cầu phát triển thực sự của nhân dân, của doanh nghiệp. Người Mỹ và EU luôn dẫn đầu trong đột phát khoa học kĩ thuật chính là vì cái này. Tàu cẩu có làm cách nào thì mãi mãi vẫn là kẻ chạy sau, vì cái hệ thống của tàu nó bị kẹt ở chính cái team vận hành quan liêu và lề mề. Nhìn xem, những đột phá công nghệ lớn nhất vẫn luôn là người Mỹ tạo ra. Chỉ một bài phỏng vấn của Everyday Astronaust với Elon Musk thực sự đáng giá gấp trăm lần mấy năm trời học kinh tế ở các trường đại học ở ..trung quốc. … | X7: [3 Ung] @hehe: Tôi thích thằng Nga hơn. Tàu cẩu đê tiện quá không hợp làm anh cả đỏ | Y7: [3 Ung] @hehe: Tôi ở Q7 thấy thằng tàu nào đâu? Toàn Hàn quốc thôi. Tàu h dạt ra khu Bình Dương thành phố mới ấy. Mà thấy sống tằn tiện khó khăn lắm. | Z7: [2 Ung] @okamoto001: trang này htông tin chính xác không nhỉ? không kiểm chứng viết gì chả được,
A8: 7 | B8: Ngân hàng ngừng hỗ trợ chuyển khoản trên 10 triệu đồng với người dùng iPhone quá cũ | C8: https://thanhnien.vn/ngan-hang-ngung-ho-tro-chuyen-khoan-tren-10-trieu-dong-voi-nguoi-dung-iphone-qua-cu-185261004084816855.htm | D8: https://voz.vn/t/ngan-hang-ngung-ho-tro-chuyen-khoan-tren-10-trieu-dong-voi-nguoi-dung-iphone-qua-cu.1285482/ | E8: 40 | F8: 30 | G8: [3 Ung] @Affectionate3245: Thấy giờ nhiều người dùng nghèo tới nổi vẫn dùng IPhone 6 Plus, sạc lighting | H8: [3 Ung] @wall-e1: đang dùng đyâ, IP6, cài mỗi cái app bank lấy OTP cho tài khoản DN có gì ngại ngùng. | I8: [3 Ung] @fearless1: Vcl xài điện thoại cùi hay gì cũng là điện thoại, đáp ứng đầy đủ chức năng, nghe gọi chuyển tiền nếu cần? Mà anh chắc ng xài ip6 plus là nghèo ko hay thằng lái chiếc mẹc nợ như chúa chổm | J8: [3 Ung] @clearwings: Chắc chắn nhé. Người có tiền tự động người ta sẽ có nhu cầu mua sắm các thứ nâng cao chất lượng cuộc sống của mình, bởi mục đích cày tiền nó là như thế. Riêng cái màn hình to hơn đã là sướng hơn hẳn rồi Trong bài báo nói ngưng hỗ trợ cho 16.7, hỏi nhanh gpt là iphone 8. Iphone 8 công nhân éo thèm xài | K8: [3 Ung] @vinata4: Ra ngân hàng mà cãi, cãi đây ai nghe mày | L8: [3 Ung] @Pavelpavlusa.003: vụ này với vụ Starbuck nó từ chối tiền mặt có một vài nét tương đồng đó, khi người ta dựng lên rào cản cho một bộ phận khách hàng “ở phía sau”. Tất nhiên ở vụ này khuyến khích anh em nhẩy sang NH khác mà xài. Chứ máy mình thích thì mình dùng, quan trọng gì cũ mới. Nó từ chối phục vụ thì tôi rút tiền sang thằng khác thôi. | M8: [2 Ung] @ghostlab: mấy dòng máy cũ Apple ngưng hỗ trợ cập nhật vá lỗi bảo mật lâu rồi, ngân hàng siết lại cũng phải | N8: [2 Ung] @mammonz: vẫn 13 và vẫn lightning | O8: [2 Ung] @WibuSimpWifi2D: Sài Android đã khác. Giờ mấy con android 12 mua từ 3-4 năm trước vãn cài app bank, vneid ầm ầm. Lêu lêu bọn sài IP cũ | P8: [1 Ung] @Vozer2k14: 17promax cần lên đời chưa nhỉ | Q8: [1 Ung] @kienthuc: cũ quá thì tự chuốc lấy rủi ro bảo mật cho mình thôi, mất tiền ráng chịu | R8: [1 Ung] @Toda Erika: Tôi bỏ tpbank được 1 năm ròii , ios16 ip11 | S8: [1 Ung] @hoahongdethuong: máy ip mình cũng ko đăng nhập được app Techcombank do nó kêu chưa cập nhập ios gì á, mà vẫn xài BIDV với VCB ầm ầm, cũng không thèm Techcombank hay TPBank lắm, mở tài khoản nhận lương thui, nghỉ cty mình cũng xóa tài khoản | T8: [1 Ung] @vinata4: Ngu, Có biết đợt bên Sing các ứng dụng covid vẫn phải tính đến thành phần yếu thế ko có smartphone k? | U8: [1 Ung] @CápTần: Quy đông đu đát hia
A9: 8 | B9: Lý do các đơn vị đồng loạt nâng dự báo tăng trưởng GDP Việt Nam | C9: https://tienphong.vn/ly-do-cac-don-vi-dong-loat-nang-du-bao-tang-truong-gdp-viet-nam-post1880728.tpo | D9: https://voz.vn/t/ly-do-cac-don-vi-dong-loat-nang-du-bao-tang-truong-gdp-viet-nam.1285436/ | E9: 35 | F9: 43 | G9: [3 Ung] @cttt: Bọn nó liên tục khoảng 20-30 năm | H9: [3 Ung] @okamoto001: Mình nghĩ VN mình giàu ngầm, số liệu khiêm tốn thôi chứ con số thật nhẹ nhàng trên 10% là ít. | I9: [3 Ung] @Eva Green: VN đỉnh hơn nhiều, thời kỳ TQ, Hàn tăng trưởng 10% là khi gdp bình quân < 5k usd, còn VN tăng trưởng 10% khi gdp bình quân đã > 5k usd, phá vỡ định kiến tăng trưởng phải phát triển công nghệ, trên thế giới chỉ có VN làm được | J9: [3 Ung] @tranhung_hn3: 5k từ những năm 70-80 thế kỷ trước anh so với hiện nay hả ? Anh có biết usd mất giá trung bình gần 4% mỗi năm so với rổ hàng hoá không. Anh có biết năm 1988 Seoul tổ chức Olympic cũng là lúc GDP Hàn đạt 5k và vừa bước chân vào hàng ngũ nước công nghiệp phát triển , Hàn tranh thủ bơm thổi về hình ảnh quốc gia hiện đại chuyển mình. Còn 5k của năm 2026 thì thua mấy thằng đang chiến tranh như Ukraina. | K9: [3 Ung] @darkkong: Chưa kể xứ này còn bốc phét giả tạo số liệu GDP nữa. Hôm nay là ASIAD 2026 kết thúc tại Nhật đây, dân mạng chửi với phẫn nộ quá trời, đc có 3 HCV, trong khi những năm trc còn dc 4,5 HCV, năm nay thằng Thái nó tận 19 HCV, gấp 6 lần xứ lừa luôn. Bóng đá VN vừa rồi thua Thái Lan thảm bại 0-2 lun. Ai đời đi thi đấu, thành tích năm sau lại thua năm trc, càng ngày càng tụt lùi đi. Xứ này trong nước thì bốc phét làm giả số liệu GDP đc, chứ ra ngoài quốc tế, chúng nó ko làm giả số HC Vàng đc thì đành chịu | L9: [3 Ung] @tranhung_hn3: Thằng Nhật cần quái gì nhảy , trước thế chiến nó đã đóng tàu sân bay , máy bay ầm ầm rồi. Năm 1925 cách đây 101 năm , Sharp đã sản xuất được radio sử dụng ống điện tử chân không: https://global.sharp/corporate/info/history/h_company/pdf_en/chapter02.pdf Toyota ra đời từ năm 1938 nó đã sản xuất ô tô ầm ầm. | M9: [3 Ung] @9635741-5: Nhật là trường hợp nền tảng xã hội, dân trí đã có từ trước rồi. Như một anh nhà giàu sa cơ trắng tay nhưng kinh nghiệm (làm cường quốc), quan hệ (với khối xanh), bản lĩnh (dân trí, tinh thần dân tộc) có thừa, khởi nghiệp trở lại không quá khó so với một anh sinh viên tò te mới ra trường, mặc dù về tiền thì cả 2 đều chỉ có tí tiền vắt túi! Cũng phải lưu ý là Nhật sau WWII mất nguyên vùng mãn châu là trái tim nền công nghiệp, hạ tầng mỏ, v.v. của cả đế quốc trước đó nên thật sự là rất kiệt quệ. | N9: [2 Ung] @nghiaagv: Nịnh tụi nó xíu không tụi nó siết room mình. | O9: [2 Ung] @BlueHills: Hàn, Nhật, TQ tăng trưởng 10% trong mấy năm lận, ae cbị đi nhé năm nay năm đầu thôi | P9: [2 Ung] @BlueHills: Không fen, 10 năm à nhưng trong 10 năm đó tụi Hàn Nhật kịp nhảy sang công nghệ cao trc khi tăng trưởng giảm | Q9: [2 Ung] @cuongtmu: Đi đêm với nhau rồi, mình mua nhiều đồ của Tây mà ko nịnh hơi phí via theNEXTvoz for iPhone | R9: [1 Ung] @nvsaygg: tư bản phương tây đã khuất phục trước nước ta | S9: [1 Ung] @ghostlab: Nhảy được đoạn công nghệ cao mới là cái khó, chứ ôm gia công mãi thì đến lúc hụt hơi khó đỡ lắm | T9: [1 Ung] @Monster in Paris: Tìm hiểu về cú nhảy của Olympic Seoul 1988 rất hay. Bước ngoặc về chính trị, kinh tế, hình ảnh quốc gia | U9: [1 Ung] @mientaythanyeu62h1: Thôi lạy...đu quá ae nào là công nghẹ cao...sục ít thôi | V9: [1 Ung] @Công lý cho gao đỏ: Phải nói là tụi nó kịp nhảy qua cnc trước khi thằng tàu tăng trưởng mới đúng , giả sử thằng tàu mà bắt đầu tăng trưởng cùng lúc với thằng Hàn thì chắc hàn giờ nó ngang con vịt vì xuất khẩu tdn ăn đc bọn tàu mà có tiền | W9: [1 Ung] @buiphamthaianh: Nếu tính GDP tăng trưởng cao thì Nhật tầm 1 chục năm chứ Hàn phải 2 chục năm, Tàu phải 3 chục.
A10: 9 | B10: Từ hôm nay, TP.HCM hứng đợt mưa lớn đến 6 ngày, có nơi trên 250 mm | C10: https://lifestyle.zingnews.vn/tu-hom-nay-tphcm-hung-dot-mua-lon-den-6-ngay-co-noi-tren-250-mm-post1687344.html | D10: https://voz.vn/t/tu-hom-nay-tp-hcm-hung-dot-mua-lon-den-6-ngay-co-noi-tren-250-mm.1285437/ | E10: 51 | F10: 33 | G10: [3 Ung] @BrownGecko: 6 ngày địa ngục lội cống vượt sông về nhà | H10: [3 Ung] @Svenska1407: Ngon, vậy tuần này nắng cả tuần rồi, cảm ơn dự báo của NN. | I10: [3 Ung] @seoitsystem: thứ 6 dự báo mưa to xin về sớm cho đã cuối cùng ... thà mưa nhỏ nhỏ lâm râm còn được đi, đằng này đéo có 1 giọt | J10: [3 Ung] @khangpham: Đang đi vệ sinh em grande ngập nước tuần rồi đây, vừa mở bộ nồi ra thợ nói liền xe anh ngập nước à 1.2tr chi phí làm mọi thứ, thay nhớt trước sau | K10: [3 Ung] @hahang83: các bạn nên thủ sẵn combo sau để tự khắc phục , hạn chế tgian phải chờ đến lượt ở tiệm nếu đen bugi, nắp chụp bugi, đồ mở bugi - có trong xe khi mua và thường là tovit 4 cạnh để mở ốp nhựa cách thay học thì youtube nhé còn nếu ngập nc qua bô rồi mà ko học dc cách tháo bô , thì vác vào tiệm bảo họ tháo bô cho, sau đó vác về nhà, tính sau nc ngập qua bô thì nên thay dầu lap và dầu máy , mở lọc gió ra xem nc có vào ko, sấy khô tạm là dc - các cái này tự học thay dc - nó rất là đơn giản, ko việc gì phải vác ra thợ lúc cao điểm tốn tgian chờ đợi chúc mọi ng an toàn, miền bắc và trung mấy hôm tới cũng đón cơn mưa lớn | L10: [3 Ung] @pegakuto: Q6 Kế bên fen nè. Gần 1 tiếng rồi. | M10: [2 Ung] @Saurus: dự báo thời tiết của xứ vệ uy tín zero, làm ăn chán vãi lồng méo tin bữa đọc báo tụi này mạnh miệng phán sắp hết mưa tè le tá lả, gì mà el nino các kiểu, sau đó mưa xối xả như gì | N10: [2 Ung] @James Bond 2025: Bình Tân mưa gần tiếng cmnr. Như trút, ko biết mấy nơi khác sao. | O10: [2 Ung] @21August9519: Tân Phú mưa lớn, sấm rền. | P10: [2 Ung] @manhpro299: 14h55 .. mưa trắng trời. | Q10: [1 Ung] @ghostlab: Cứ đoạn nào trũng là y như rằng xác định thím ạ, dắt bộ vài bận là đói kém luôn | R10: [1 Ung] @Không nói nhiều: Mọi năm cỡ ngày này thì miền Trung thay nhau mưa kỷ lục. Năm này mưa kỷ lục dời vô SG. Nhớ tháng 10 hai năm liên tiếp Đà Nẵng mưa kỷ lục | S10: [1 Ung] @Tommaso Schelotto: Ahi hi hi, đồ thành phố " via theNEXTvoz for iPhone | T10: [1 Ung] @khangpham: Cả 2 thím ui, chạy đường ngập sau đó về nhà ngập cả đêm nữa Ra bảo trì vệ sinh nồi, kim xăng, thay nhớt, lọc gió và cái dĩa kg biết lội nước sụp hầm gì mà nó cong luôn Xe vk chạy
A11: 10 | B11: Kỷ nguyên năng suất mới của AI hiện thân: Việt Nam – Trụ cột Đông Nam Á | C11: https://vtcnews.vn/ky-nguyen-nang-suat-moi-cua-ai-hien-than-viet-nam-tru-cot-dong-nam-a-ar1043094.html | D11: https://voz.vn/t/ky-nguyen-nang-suat-moi-cua-ai-hien-than-viet-nam-tru-cot-dong-nam-a.1285452/ | E11: 38 | F11: 28 | G11: [3 Ung] @malacat: Ta nói : ngày nào cũng sục rồi bắn tung tóe thì hại thận lắm | H11: [3 Ung] @tntltct2: Ý anh là giống vầy hở, AI éo âu, từ hồi rộ bờ lốc chen, en ép ty đã có rồi | I11: [3 Ung] @Effoc: Má nhìn thiểu năng trí tuệ thật chứ, thằng nào nghĩ ra cái này đã ngu mà mấy thằng lên chạm tay ngu x10 | J11: [3 Ung] @ghostlab: Cứ phong trào công nghệ nào nổi lên là y như rằng lại có quả nghi thức chạm tay mở màn quen thuộc | K11: [3 Ung] @flame1602: Thì nó giống nghi lễ đám cưới vậy đó, thấy ngta làm thì mình làm thôi, có đứa nào đặt câu hỏi là tại sao phải cắt bánh, tại sao phải rót rượu đâu đủ hào nhoáng để làm đẹp chương trình là được. | L11: [3 Ung] @HugoBoss.94: Bớt mõm | M11: [2 Ung] @Eva Green: Về khoản bú trend thì dân VN làm trùm, từ AI, blockchain, 4.0, 5G, robot, bán dẫn, úp bô xong thì nhảy trend khác | N11: [2 Ung] @vinata4: Cái xứ vẹm này, do OS rác sẵn, nội lực đéo có gì, nên mỗi triều đại chỉ là sự lặp đi lặp lại của combo sục-bắn-ngạo nghễ xong ai về nấy, iqcow hạ cánh trời tây, dân đen zombie tiễp tục sống như chó lợn cha truyền con nối. | O11: [2 Ung] @HugoBoss.94: Có cđb thì có đó | P11: [1 Ung] @ChimSaCaNoi: nể ông nào lm ra dc quả "chạm tay màn hình mở khóa kỷ nguyên AI". h đọc báo cứ có cái gì liên quan AI là y như rằng có cái "nghi thức" này | Q11: [1 Ung] @LingZhi: Nhìn bảng tổng huy chương vàng asiad là biết | R11: [1 Ung] @Monster in Paris: Cũng may là còn văn "nước ta còn nghèo, mới trải qua xxx" chứ giàu lên 1 tý có khi Tàu cộng, Mẽo đế cũng chỉ là cái tên.
A12: 11 | B12: Khu văn hóa du lịch tâm linh Giếng Tiên kinh phí trên 200 tỉ của nghệ sĩ Quyền Linh giờ ra sao ? | C12: https://tuoitre.vn/khu-van-hoa-du-lich-tam-linh-gieng-tien-kinh-phi-tren-200-ti-cua-nghe-si-quyen-linh-gio-ra-sao-10026100406574704.htm | D12: https://voz.vn/t/khu-van-hoa-du-lich-tam-linh-gieng-tien-kinh-phi-tren-200-ti-cua-nghe-si-quyen-linh-gio-ra-sao.1285494/ | E12: 22 | F12: 15 | G12: [3 Ung] @CápTần: Cho đàn em chôn tượng, rồi về đào lên ..... Cũng phường úp bô thôi Trùng hợp quá | H12: [3 Ung] @Triển Chiêu Cấp 3: Xui thôi. Chứ vụ này không phải vì ông trời đâu. Kịch bản "phim" rất đẹp: mua đất an dưỡng -> đào lên gặp tượng -> thấy linh thiêng nên thờ -> phao tin là nhiều người khuyên nên mở du lịch tâm linh theo sự hiển linh mà tượng giao phó (cái này là xaolol) -> Vừa xây vừa huy động từ thiện, nộp tiền mua phước giải nghiệp. Thực ra ban đầu đã có mưu đồ xây khu du lịch tâm linh nên viết KỊCH BẢN này. Xui cái đợt 2020 sư quốc doanh start-up hàng loạt chùa, nhiều quá, đó là chưa kể bọn buôn thần bán thánh vũ hoa sen chiêu bài mở phim-sẽ đuổi nico ở tịnh xá để chùa mình kinh doanh thuận lợi; rồi hàng loạt cái gọi là "thiền viện trúc lâm" mọc lên như nấm khắp địa phương (nghe đâu giới đầu tư tâm linh ngoài Bắc xây cả hệ thống làm ăn rất phất). Nói chung, kịch bản "phim" quá, mà dựng tượng Phật thì khó cạnh tranh đám kể trên, nên hắn dựng nhân vật tín ngưỡng theo người K… | I12: [3 Ung] @luvFany: Sợ đồn nên anh mc boôk báo luôn cho chắc cú | J12: [2 Ung] @huycreative: Ông trời có mắt | K12: [2 Ung] @RanYakumo: Mịa, hèn gì mấy năm nay rao bài lọ lem hạt dẻ cật lực, thuê cả dalit vozer kéo bài về f33 chào hàng mà flop quá không có phú nhị đại hay vozer tinh anh nào ngó ngàng. Chú linh cũng đi lên từ nghèo khó, có tài nhưng lại tham lam muốn lên đến đẳng cấp buôn thần bán thánh, giờ thánh quở, nghiệp nó quật không trượt phát nào. | L12: [1 Ung] @hongduc11: Liệu thứ 6 tuần sau chúng ta có đối tượng bố vợ | M12: [1 Ung] @crv2018: Ăn của thiên hạ rồi cũng dính nghiệp Có cỡ 100 tỷ gửi bank tháng lãi gần 1 tỷ rồi đi chơi vòng quanh thế giới ko sướng hơn sao
A13: 12 | B13: (Mỹ) (Dịch) Ông Trump nói hối tiếc vì đã đề cử các thẩm phán Tòa án Tối cao Gorsuch, Barrett và Kavanaugh | C13: https://www.reuters.com/legal/government/trump-says-he-regrets-nominating-supreme-court-justices-gorsuch-barrett-2026-10-01/ | D13: https://voz.vn/t/my-dich-ong-trump-noi-hoi-tiec-vi-da-de-cu-cac-tham-phan-toa-an-toi-cao-gorsuch-barrett-va-kavanaugh.1285422/ | E13: 17 | F13: 32 | G13: [3 Ung] @Nike CEO: chắc vẫn cay cú vụ thuế tariff bị toà tối cao tuyên vi hiến một thất bại lớn trong lịch sử | H13: [3 Ung] @V for Universe: K biết maga có suy nghĩ là họ vốn dĩ bảo thủ mà họ còn k chịu nổi vs các quyết định của hay k, à chắc là... "Tôi thích sự trung thành, đúng vậy," Trump nói với người phỏng vấn, người sau đó hỏi liệu đó có phải là điều ông muốn từ các thẩm phán hay không. "Không, tôi không muốn lòng trung thành." "Tôi muốn có những quyết định đúng đắn," ông Trump nói.", lều reuters thâm đó. | I13: [3 Ung] @DMTTCM: Hề cam mà bổ nhiệm bọn ma gà trong voz là ngon rồi, toàn pet trung thành | J13: [3 Ung] @haylamem: Thổ tả đọc 1 bài báo và những gì tồn tại trong não chúng nó là sự hả hê. Đúng là brainrot! Ko cứu nổi lũ thổ tả | K13: [3 Ung] @ghostlab: Vụ đó dội gáo nước lạnh thật, tưởng chọn người nhà thì dễ bề phán quyết ai ngờ lại gậy ông đập lưng ông | L13: [3 Ung] @le0.writer: Thời thế đảo điên, lũ Trump con chê người khác brainrot Nhưng điểm báo về thành công tự nhận của bố chúng là chúng nó tung hô, đấy là content chất lượng | M13: [3 Ung] @maybe990: Các anh tưởng thật à . Thực ra 100 quay xe thôi , nếu tự mình quay xe thì hơi ngại nên cho mấy thằng đệ ngáng đường để danh chính ngôn thuận quay xe ,chứ áp vào thật thì nát thật sự Trong bài 100 đã nói rõ rồi . " ông thích những quyết định đúng đắn " | N13: [3 Ung] @le0.writer: Diễn quá đạt Tôi đề nghị lập một ban chuyên giải thích phát ngôn và hành động của Trump sau đó viết thành sách, tương tự như với các Phúc âm | O13: [3 Ung] @king1993: Cười ỉa mới tụi maga luôn, lúc supreme court cho ra phán quyết có lợi cho giáo chủ ấu dâm của tụi nó thì là thượng tôn pháp luật, còn lúc ra phán quyết bất lợi thì tụi maga chửi như con chó luôn, nào là bị mua chuộc, thổ tả, bla bla. | P13: [3 Ung] @Agent Orange: Con chúm tro này nếu mà được làm lãnh đạo ở một nước không phải là mẽo thì nó đã sửa hiến pháp cho toà án thành bù nhìn để một mình nó quyết hết cho nhanh rồi. | Q13: [1 Ung] @maybe990: Anh lại xuyên tạc rồi . quyết định của ông ấy luôn đúng vậy việc đề cử ba thẩm phán Tòa án Tối cao theo anh là nghĩ ông ấy nói là sai hay đúng
A14: 13 | B14: Bệnh nhân muốn mổ sớm, bác sĩ hướng dẫn 'gửi bao thư' | C14: https://tuoitre.vn/benh-nhan-muon-mo-som-phai-gui-bao-thu-100261003093823933.htm | D14: https://voz.vn/t/benh-nhan-muon-mo-som-bac-si-huong-dan-gui-bao-thu.1285489/ | E14: 30 | F14: 9 | G14: [3 Ung] @Saga Pattern: đợt bị tai nạn gãy tay nằm 1 tuần mới dc mổ trong khi thấy ai cũng dc mổ ngay hoá ra là phải đi dky mổ dịch vụ mới dc thấy mình hai lúa thật | H14: [3 Ung] @liberia2010: Nếu mà mấy cái bv đa khoa tuyến tỉnh nó có năng lực thì dân đen éo phải lận đận bắt xe đò lên tuyến cuối, nằm vật vạ ngoài hành lang các kiểu để chờ được khám chữa bệnh. | I14: [1 Ung] @mapkuto3: Có lẽ lúc đau ốm bệnh hoạn thì nền kte thị trường mới thể hiện rõ nét nhất Ai muốn nhanh gọn, lẹ, giờ đẹp, chữa tốt....thì chịu khó chi mạnh là êm xuôi ( vẽ ra câu từ mỹ miều là Dịch Vụ) Ai k có thì cứ theo quy trình Xưa khám cũng cần mổ xẻ nhỏ. Theo dịch vụ mắc gấp vài lần nhưng giải quyết nhanh trong tuần Còn muốn theo quy trình thì trong tháng, ngta sẽ điện liên hệ sau Sent from Xiaomi 2512BPNDAG via VOZVNApp | J14: [1 Ung] @dacnhiem: Bệnh thành tích nó ăn vô tận nghề này nhé, BV tỉnh còn ko cấp giấy chuyển viện lên tuyến trên vì sợ đánh giá kém và cứ ngâm bệnh đó đến khi người nhà quậy um mới cho chuyển, kỳ BV chỗ tôi tay kia vào cấp cứu TNGT bị đòi cưa chân nhưng người nhà nói ko đòi lên Chợ Rẫy nhưng BV ban đầu kiên quyết ko cho chuyển sau người nhà quậy tới GĐ BV thế là được đi nhưng phải cam kết ko quậy BV, lên CR thế là giữ được cái chân, bảo sao BV CR luôn quá cmn tải.
A15: 14 | B15: [Dịch]Vui chơi quốc khánh Trung quốc đông nghịt, nhưng sức mua yếu. Một bát lòng bò, mấy người cùng chia nhau ăn thử hỏi doanh thu được bao nhiêu? | C15: https://www.macaodaily.com/html/2026-10/03/content_1937687.htm?utm_source=chatgpt.com | D15: https://voz.vn/t/dich-vui-choi-quoc-khanh-trung-quoc-dong-nghit-nhung-suc-mua-yeu-mot-bat-long-bo-may-nguoi-cung-chia-nhau-an-thu-hoi-doanh-thu-duoc-bao-nhieu.1285348/ | E15: 35 | F15: 43 | G15: [3 Ung] @Sầu đời: Đm, tàu cẩu năm nay nát quá. Đến độ cửa hàng còn không dám nhập hàng về bán dù là quốc khánh là hiểu rồi. Mà nhìn u ám thế này nhập hàng về lỗ chắc. | H15: [3 Ung] @Hoa Ly: Thương nhân dân Trung quốc quá! Nãy tôi có đọc bài thì thương dân Mỹ phải mua nhà giá trả lãi cao khủng khiếp, rồi dân châu Âu tốn 100 tỏi chênh để mua dầu Mỹ khiến đời sống nhân dân châu Âu lầm than, còn nhân dân Nhật thì ngập lụt mưa liên tục trong thời gian dài. Đúng là khi Cuba dạo này ít canh giữ hòa bình vì mất điện, thì đã có VN của tôi xứng đáng là anh cả làm thay việc của người bạn Cuba. Cảm ơn các nhà báo có tâm và cộng tác viên voz đã mang những bài viết ý nghĩa như thế này về, để tôi có thể ăn cơm ngon hơn khi nghĩ về thực tại Trong sự khó khăn của toàn thế giới, chỉ có một điểm sáng là GDP nước tôi đã tăng gần chạm 2 con số. Xem vtv, tôi xúc động không kìm được nước mắt. Các chỉ số việc làm, lương tăng, thất nghiệp thấp, người lao động được làm những công việc tận dụng kĩ năng của họ, fdi tăng, giải ngân tăng, dự án tồn động được khơi thông,... | I15: [3 Ung] @Thongthiengiaochu: Tình hình chung là TQ khó khăn hơn năm trước là đúng nhưng không nát như lều báo viết đâu. Vừa về hôm qua, lòng bò thì không rõ mấy người ăn 1 bát nhưng vào outlet của nó thấy dân TQ mua hàng hiệu ầm ầm. Adidas, nike...mua 3 chiếc giảm 50%, thanh toán xếp hàng dài. | J15: [3 Ung] @chuadaonguyen: Đổi nick rồi hả chủ thớt, điểm baó thôi mà cũng bị ban à | K15: [3 Ung] @Đừng Xanh Như Lá: Tổng Nga Ngú điểm báo về Trung Quốc. Sao ko điểm báo U cà đang rãy chết hả Pú Chink ? | L15: [3 Ung] @choregnickchuavay: mẹ nó, đồ ăn trung quốc to vl, nhà tôi đi 3 người gọi 2 phần chia ra ăn còn no, gọi 3 phần thì chỉ có bỏ lại chứ k ăn nổi tính ra đi du lịch trung khoảng ăn uống lợi vãi ra, | M15: [3 Ung] @Make Y.Maga Great Again: h voz đang có PLC điểm báo TQ trong cơn giãy chết đạch đạch đạch nhé fen hoài niệm về thời "Mỹ trong cơn giãy chết" | N15: [3 Ung] @agree11: Anh @NDMan bị Cổ màu hành thích rồi nên từ giờ dùng acc này à | O15: [3 Ung] @zayken: Tôi vừa đi 1 vòng Hạ Môn về cách đây 2 tuần. Ra phố đi bộ Zhongshan Road vào chiều chủ nhật mà thấy hơi vắng vẻ. Ngồi nghỉ chân chém gió với ông chủ quán trà ô long ở phố đi bộ, thấy kêu năm nay làm ăn khó khăn hơn, lượng khách mua hàng giảm hơn nửa. Tạt vào shop 3 dòng kẻ múc 2 đôi giày thể thao cho vợ, ngồi hít điều hoà nửa tiếng mà thấy hơi vắng vẻ đìu hiu. | P15: [3 Ung] @YOASOBI_: Bọn tàu sang hàn quốc du lịch , ngồi máy bay mấy tiếng tới hàn buổi sáng xong ra ga dongdaemun lên xe buýt đu tua luôn , tranh thủ lúc di chuyển giữa các địa điểm thì ngủ trên xe buýt chứ không thuê khách sạn , mùa đông trời lạnh mấy ngày ko tắm cứ vậy tới lúc lên máy bay về lại tq via theNEXTvoz for iPhone | Q15: [2 Ung] @Dr Lê Thẩm Dương: Cái này tính riêng ở Ma Cao thôi mà | R15: [2 Ung] @xiaoer237: cũng tùy khu vực nữa, đi mấy khu đông bắc thì đúng kiểu người khu vực khác đến gọi 1 2 món cho 4 5 người ăn cmnl, còn ở mấy khu đắt đỏ thượng hải các kiểu thì nó cũng na ná ở Việt Nam. Nhưng đúng là ở bên đấy nếu ăn đồ đắt thì đa số nó cũng là lấy số lượng khá nhiều. Xem mấy cái review đi ăn ở TQ thì 1 là rẻ mà nhiều vcl, 2 là đắt mà ít vcl, 3 là đắt là nhiều vcl | S15: [2 Ung] @giayasics: sợ chưa, coi chừng đến fen đấy | T15: [1 Ung] @Huỳnh Cẩm Vy: U ám vậy | U15: [1 Ung] @dungbeo09: Hết trung thu rồi đến quốc khánh, xin nghỉ 1 lèo đi chơi sướng nhỉ | V15: [1 Ung] @agree11: Hình như banned có thời hạn thì acc vẫn search được Ban khoảng 1 năm chẳng hạn | W15: [1 Ung] @lamson_2372007: Oh Tàu giờ cũng làm tuần lễ vàng giống Nhật luôn.
A16: 15 | B16: Trực thăng Mi-8 của Nga bị bắn hạ do 'hỏa lực thân thiện' từ một chiếc Su-35 | C16: https://giaoducthoidai.vn/truc-thang-mi-8-cua-nga-bi-ban-ha-do-hoa-luc-than-thien-tu-mot-chiec-su-35-post794801.html | D16: https://voz.vn/t/truc-thang-mi-8-cua-nga-bi-ban-ha-do-hoa-luc-than-thien-tu-mot-chiec-su-35.1285364/ | E16: 29 | F16: 38 | G16: [3 Ung] @deckelrand7: Cứ trúng là được rồi. | H16: [3 Ung] @orlagu: Phòng không không quân Nga: “Đến quân mình tao còn bắn thì bọn phát xít chúng mày cứ liệu cái thần hồn.” | I16: [3 Ung] @174cm: Trúng mục tiêu quân sự là thành công rồi | J16: [3 Ung] @Bát Hoàng Đế: Friendly fire = hoả lực thân thiện ? Clm lều dịch thuật tếu vkl, được đó | K16: [3 Ung] @khelo: Tính ra tên lửa nga bắn máy bay nga với máy bay dân sự tốt phết . | L16: [3 Ung] @Cu Em Hip Hop: Bắn trúng là đã khó lắm rồi. Đừng hỏi bắn trúng ai được không | M16: [3 Ung] @porpro84: Dễ hiểu, chuyện friendly fire diễn ra như cơm bữa. Bất cứ chiến dịch nào cũng có. Cơ mà trách thì vẫn phải trách thôi. À đây cho ai phản biện. | N16: [2 Ung] @BlueHills: Tu-95MS cũng do ko quân Nga bắn nhầm | O16: [2 Ung] @StoneCold166: Tai nạn thì nước nào cũng bị nhưng biến nó thành truyền thống quý báu thì chỉ Nga mới có. https://news.yahoo.com/russian-air-defenses-shot-down-142900056.html | P16: [1 Ung] @Thanh Niên Thô Kệch: friendly fire dịch ra nghe hài phết | Q16: [1 Ung] @checkmate2022: Giết nhầm còn hơn bỏ sót. | R16: [1 Ung] @Agent Orange: Cứ đồ Nga bắn đồ Nga là có tỷ lệ bắn chính xác cao nhất. Giờ mà đệ đái ra lệnh phóng nuke thì có khi nuke nó lại rớt ngược xuống đất ngú vì thích "vs Nga" thì bm. | S16: [1 Ung] @deckelrand7: Hoặc ví dụ này nữa. Ko cần tên lửa người Nga vẫn tự hạ được trực thăng của mình https://twitter.com/x/status/2106379007503863892 | T16: [1 Ung] @chi_tai_ham_ca_do: là sao? fen có đọc cap của cái clip không? | U16: [1 Ung] @ghostlab: Hệ thống nhận diện ta - địch kiểu này dễ lỗi quá nhỉ | V16: [1 Ung] @deckelrand7: Thì tôi nói có cần tên lửa đâu, chỉ cần chút vodka làm việc là được.
A17: 16 | B17: 'Đọc' suy nghĩ của đàn ông ngoại tình | C17: https://giaoducthoidai.vn/doc-suy-nghi-cua-dan-ong-ngoai-tinh-post794712.html | D17: https://voz.vn/t/doc-suy-nghi-cua-dan-ong-ngoai-tinh.1285498/ | E17: 16 | F17: 4 | G17: [2 Ung] @hoangvu322: Nói thật: Thằng đàn ông nào chả có tư tưởng ngoại tình, chẳng qua không có cơ hội thể hiện | H17: [1 Ung] @cruelpham: Tôi thấy vớ va vớ vẩn, đàn ông ngoại tình giấu vợ hầu hết là vì tình dục, cái đầu trên không làm chủ cái đầu dưới thì nó vậy thôi. Riêng về việc phụ nữ ngoại tình thì lắm thứ phải thắc mắc, hôm qua, ngay tại F33 này, tôi nhớ không nhầm bài báo về cả hai vợ chồng ngoại tình, một anh vozer cmt thế này: “ Tôi không biết tại sao, em nó xinh, có học thức nhưng chồng chỉ biết quăng tháng 55-75 triệu tự tiêu, tự chăm con, cảm thấy không được quan tâm mới bập vào một thằng như tôi, biết chiều chuộng, biết lắng nghe, quan trọng là đ… khoẻ, 4-5 nháy/ ngày ( xin lỗi anh em và min mod, nguyên văn nó chính xác như thế)” Lẽ ra câu hỏi Khi ngoại tình đằng ấy nghĩ gì? nên là thắc mắc đàn ông dành cho phụ nữ vì thực tế những thằng mà cô ta ngoại tình chỉ chăm chăm vào nhu cầu xác thịt hoặc lừa tiền là chính | I17: [1 Ung] @ghostlab: vẽ vời ra lắm lý thuyết cao siêu làm gì, tóm lại cũng chỉ vì ham của lạ mà thiếu bản lĩnh thôi
A18: 17 | B18: Tỷ lệ sinh viên tốt nghiệp giỏi, xuất sắc ở các trường đại học cao mức nào? | C18: https://dantri.com.vn/giao-duc/ty-le-sinh-vien-tot-nghiep-gioi-xuat-sac-o-cac-truong-dai-hoc-cao-muc-nao-20261002214304331.htm | D18: https://voz.vn/t/ty-le-sinh-vien-tot-nghiep-gioi-xuat-sac-o-cac-truong-dai-hoc-cao-muc-nao.1285238/ | E18: 33 | F18: 20 | G18: [3 Ung] @BrownGecko: Xưa thi đại học ỉa ra quần dc 24, học ỉa ra quần mới ra khỏi trường dc 7.x | H18: [3 Ung] @Naruto1001: Chủ yếu khối ngành kinh tế thôi, chứ kỹ thuật thì dù tỉ lệ tăng so với hồi xưa nhưng thua xa đám kinh tế. Xuất sắc mà chiếm trên 30% trở lên thì cái xuất sắc đó vứt cho chó gặm được rồi. Tụi tuyển dụng nó ưu tiên tuyển mấy đứa xuất sắc thật hả? | I18: [3 Ung] @SunGlory1010: Mà không biết chương trình học của khối kinh tế ntn. Chứ chương trình học của khối kỹ thuật là bố của nặng. Nặng cả về lý thuyết và đồ án môn học. Chưa cần biết là có outdate không, nhưng chắc chắn 1 thằng sv kỹ thuật tốt nghiệp được nó có kiến thức cơ bản nhất về nghề nó phải làm. Cái nó cần là kinh nghiệm hiện trường mà thôi. Mà tôi cảm thấy giảng viên môn kỹ thuật nó cũng gắt hơn thật, hoặc là khô khan hơn, thi thì toàn vấn đáp, bố của ác. | J18: [3 Ung] @zzkaka: Rác rưởi. Đm bộ dục, bạn tao giảng viên mấy đứa chia sẻ mới biết giờ sinh viên cũng phải có kpi ra trường, tốt nghiệp. | K18: [2 Ung] @okamoto001: giỏi, lớp đại học tôi tốt nghiệp toàn trung bình khá là nhiều, thị lại thì lia lịa | L18: [2 Ung] @traidepdebepgaixinh: nhìn sang ftu chắc vượt luôn chỉ tiêu, buff cho các em sinh viên full xuất sắc 1/4 lượng sinh viên, đá sang hust không ngóc nổi 3% giỏi ấy chứ tưởng | M18: [2 Ung] @Doanh Chính - Thủy Hoàng: Do giáo trình khối kinh tế vẫn vậy. Đề thi thì các thầy cô lười nên xào nấu lại đề cũ. Các cháu chỉ chăm chăm ra tiệm photo mua đề mấy năm trước về học tủ. Học xong chả nhớ mô tê gì. Éo mẹ sinh viên trường kinh tế và kiến thức cơ bản quên sạch. Ngay môn kinh tế học vi mô đã dạy thuế của chính phủ gõ lên ai thì hai bên mua bán đều bị thiệt hại, mức độ thiệt hại không liên quan đến gõ đầu bên nào mà phụ thuộc vào độ dốc đường cung cầu. Giờ các cháu cũng éo biết. | N18: [1 Ung] @okamoto001: anh có con chưa, đi họp phụ huynh cô giáo lớp 1 còn có KPI đăng ký lớp sẽ có bao nhiêu em xuất sắc, bao nhiêu đạt..... đầu năm chưa biết đầu vao mầm non như nào đã KPI rồi | O18: [1 Ung] @ghostlab: Bên kỹ thuật mà rớt môn hay nợ đồ án là xác định ở lại trường ngắm hoa phượng dài dài chứ đùa đâu
A19: 18 | B19: Bangkok ngày 27-9, vẫn chìm trong biển nước | C19: https://tuoitre.vn/bangkok-ngay-27-9-van-chim-trong-bien-nuoc-100260927165830628.htm | D19: https://voz.vn/t/bangkok-ngay-27-9-van-chim-trong-bien-nuoc.1283600/ | E19: 65 | F19: 68 | G19: [3 Ung] @lady_may_cry: có thông nệ cuốc tế rồi, mấy con ong ve đừng có ca thán nữa nhé | H19: [3 Ung] @chim2dau: Cơ sở hạ tầng thái lan đi trước đông lào 50 năm - ai đó said | I19: [3 Ung] @putinkaa: Thái Lan ko biết mời các chuyên gia vẩu dơ sang hỗ trợ à? | J19: [3 Ung] @ConVịt Con: Đó lâu lâu mới ngập người dân không có kinh nghiệm đối phó. Ở ta tạo điều kiện mỗi năm dềnh đôi ba lần từ trẻ con mẫu giáo đến cụ già xưa nay hiếm đều có kinh nghiệm sống chung với dềnh không phải cứu trợ. | K19: [3 Ung] @ghostlab: Mưa dồn dập vượt 300mm mà lại trúng triều cường thì hệ thống kênh rạch nào thoát kịp bác, nước cứ ứ lại chứ có chỗ chứa đâu | L19: [3 Ung] @Steven Nguyen: Đúng là báo chí VN thiệt chớ. Tui đang ở Bangkok mà nghe mô tả tưởng nơi mình đang ở là 1 meta nào đó. Tình hình ở Bangkok là chia làm 2. Bên ngập là phía đông nam thành phố kiểu quận 2, quận 7 của SG. Khu trung tâm bờ đông dọc bờ sông kiểu hoàng cung, china town đồ cũng ko ngập. Còn bên phía tây thì khô ráo, dân ăn chơi nhảy múa như ko có gì Ngập nặng là ngày 26/09 thôi, chứ hum wa thì ở khu trung tâm Sukhumvit thì nước rút hết rồi. Chỉ còn 1 số quận màu xanh vùng đông nam thì còn ngập nặng nước đến lưng quần. Hum wa các em hot girl đi ra quay content các kiểu rồi chứ có thảm họa mẹ gì như báo chí VN viết đâu | M19: [3 Ung] @vandeptrai: ở đâu cũng thế thôi, cứ mưa to kèm dài ngày thì cũng ngập lụt hết. Tôi đang ở Nhật, cụ thể là ở Chiba đây, mưa to cái cũng ngập hết. Đợt này còn đỡ chứ đợt tháng trước còn dừng hết cả tàu, sân bay Narita thì bị cô lập tại ko di chuyển đến đấy được, mấy quán ăn thấp thì ngập đến rốn | N19: [3 Ung] @Master Cax: chuyện mình lo chưa xong cứ đi lo cho thằng khác ! Thật sự đéo hiểu kiểu gì | O19: [3 Ung] @nguyend9x3: chủ yếu đăng cho mấy thằng chuyên bỉ bôi vn ngập do quản lý vs cơ sở hạ tầng yếu kém nhất là mấy thái nô toàn tung hô cơ sở hạ tầng thái dúi xịn xò đi trc vn 50 năm | P19: [3 Ung] @Steven Nguyen: vậy là cố tình tung fake news hả bạn? | Q19: [3 Ung] @chanhday173: báo Vịt méo đâu mà a lại chửi nhỉ, cũng lấy tin từ AP về dịch lại thôi | R19: [3 Ung] @Rainy75: súc vật tự nhục ko thích điều này | S19: [3 Ung] @Steven Nguyen: Bớt giỡn đi bạn. Từ trung tâm Bangkok ra đến biển ở vịnh Thái Lan khoản 40 km. Bangkok nó còn có cả 1 quận ở ngay bờ biển là Bang Khun Thian màu đỏ đó . | T19: [3 Ung] @Tommaso Schelotto: Thằng khác bị gì thì bênh tới bênh lui, mình bị gì cái là chửi tanh bành, very Vietnamese | U19: [3 Ung] @Rainy75: lũ chó bất mãn ấy mà, nước nào cũng sẽ luôn có 1 giống loài như thế | V19: [2 Ung] @L=18cm: Anh ở BK confirm giúp tin chính phủ TL ban bố thảm hoạ là thật hay báo chí VN chém ra thế. Báo VN thì cũng mang tin từ bển về chứ đâu , lên tiktok FB tụi tây với dân TL post bài quá trời, dĩ nhiên là ko đến mức thảm hoạ nhưng bảo ăn chơi nhảy múa như ko có gì thì là bốc phét. | W19: [2 Ung] @Steven Nguyen: Bờ tây ko có ngập nên dân vẫn sinh hoạt bình thường. Tôi nói ăn chơi nhảy múa là kiểu dân vẫn sinh hoạt bình thường. Chứ tất nhiên, ko có dân nào tổ chức party live stream ăn chơi nhảy múa đồ giữa lụt lội chọc cho dân vùng bị ngập lụt chửi ha Cái thảm họa bạn nói là công bố tình hình thảm họa dựa theo luật tình hình thảm họa là có. Mục đích là để có quyền huy động lực lượng quân đội, cảnh sát.. ứng cứu, sử dụng quỹ phòng chống thảm họa... Giống như kiểu Mỹ công bố tình trạng khẩn cấp 1 năm chắc mấy chục lần vậy á | X19: [2 Ung] @Master Cax: ngu vcc, cái này có gì đáng tự hào à thằng cc red cow | Y19: [1 Ung] @Vanguard_VietNam: Làm nhớ lại Phú Yên năm ngoái | Z19: [1 Ung] @nhm2409: ủa ngập cũng 2 ngày rồi mà chưa xong hả, đọc báo trước thấy tổng 300mm mưa trong 2 ngày chứ có nhiêu đâu
A20: 19 | B20: Quyền Linh lên tiếng khi bị nhắc tên giữa vụ án An Cung giả: Khẳng định không liên quan | C20: https://laodong.vn/van-hoa-giai-tri/tung-duong-quyen-linh-hoa-minzy-cung-sao-viet-an-mung-tuyen-viet-nam-vo-dich-1757049.ldo | D20: https://voz.vn/t/quyen-linh-len-tieng-khi-bi-nhac-ten-giua-vu-an-an-cung-gia-khang-dinh-khong-lien-quan.1282739/ | E20: 89 | F20: 52 | G20: [3 Ung] @ghostlab: Cứ thấy có phốt là mạng xã hội lại tự phong phóng viên đi kết tội trước, gặp mấy vụ này cứ lôi đơn ra kiện vài đứa làm tới nơi tới chốn mới chừa thói câu tương tác bẩn | H20: [3 Ung] @chuchotrungthanh02: Đéo bắt thằng này thì đúng là nát, thằng này suxsinh lắm nó quảng cáo sữa giả này kia nhưng nói là không hình ảnh giả, thằng này nó làm ăn bất chính sống mất dạy nhưng lên tivi báo đài thì đep tổ ong các kiểu, hi vọng nó vô tù, nó vô tù tôi nguyện làm bò đỏ 7 ngày | I20: [3 Ung] @vozchoregnick3: Thôi ông im mẹ cái mồm đi. 1 vụ thì người ta còn hoài nghi chứ vụ đ nào cũng có mặt mà kêu không liên quan. | J20: [3 Ung] @Củ Chi Gym: Bắt thằng này tôi làm bò đỏ 1 năm | K20: [3 Ung] @medusa: Thằng này đạo đức giả còn hơn th Linh 14 tỏi | L20: [3 Ung] @Agent Orange: Thì từ vụ Link14 trở đi thì mainstream của vẩu dơ mới chuyển sang chửi showbitch, chứ trước đó thì toàn showbitch nô thôi. Với lại cũng do thay đổi độ tuổi nữa, 10 năm trước vẩu dơ F33 đa số là những thằng 2x sinh viên hoặc mới ra trường còn nhí nhảnh thấy bọn giải trí là bú theo, còn hiện tại cũng những vẩu dơ đó nhưng đã trở thành những thằng U40 lúc nào cũng nghi ngờ nhân sinh và chửi. | M20: [3 Ung] @chuchotrungthanh02: Ủa dm, vậy thì chối làm ccc gì vậy? Còn lên nói do AI ghép các kiểu, mà ghép bao năm đến lúc bị khui sữa giả thì nói vậy? Mài hiểu mài đang nói gì không? | N20: [3 Ung] @chuchotrungthanh02: Sợ nó còn book bài mạnh hơn nếu thoát nạn vụ này để tẩy trắng ấy, nên tốt nhất là đang trong diện điều tra và tuần sau tạm giam là đẹp, nguyện tăng lên 1 tuần nữa làm bò đỏ 2 tuần | O20: [3 Ung] @boyloinhoi: Tóm tắt : Có tin đồn cty do QL đứng tên đã từng góp vốn vào cty sản xuất An Cung giả QL lên báo đính chính mình không liên quan gì đến sản phẩm An Cung giả Nói chung thằng viết tin chẳng có gì sai trong cái nội dung thông tin đó cả, còn chú QL thì đang cố bẻ hướng dư luận theo hướng "tui ko có quảng cáo thuốc giả " thay vì trả lời câu hỏi "có góp vốn thiệt hông?" | P20: [3 Ung] @duy289: đã lên bài khóc dm chính thức gọi là t lol chứ bố bố cái cc via theNEXTvoz for iPhone | Q20: [2 Ung] @quang77: bố tìm được con rể chưa? | R20: [2 Ung] @Cửu Thiên Tiên Đế: Nghe nói cấm xuất cảnh, có không nhỉ ? | S20: [2 Ung] @eddy: 2k9 live bằng Yahoo à ? | T20: [1 Ung] @Kim Tiêm: Bố có đi viện thì cũng ko sao, bên ngoài đã có con chăm Lọ Mlem rồi | U20: [1 Ung] @LightX9: Uhm, tôi cũng có nghe nói cấm xuất cảnh + phong tỏa tk. Chuẩn bị ngày lành tháng tốt mà triển thôi. | V20: [1 Ung] @Thuongdebequanam: Lạy bố khởi nghiệp đại diện hình ảnh phi lợi nhuận,bố nuôi vợ con bằng giấy à??? | W20: [1 Ung] @vitomxau_88: Ông nào cũng kêu vô tội trước khi bị nhập kho . | X20: [1 Ung] @Davil: Nó cũng mới kiếm tiền nhanh từ khoảng chục năm trở lại đây thôi. Lựa fame để chơi quảng cáo cho đội mmo bán sữa giả, đông y tpcn giả dược. Chắc cũng phải góp vốn không ít với đội này. Cái thời kỳ mà vozer kêu là “dễ kiếm tiền” đấy chứ đâu, thực chất là giai đoạn vô pháp vô thiên, kinh doanh bất chấp. Thằng này tôi đánh giá phải gây hại gấp 10 lần lũ ông tiên từ thiện kia, vậy mà chưa bị bế. Thì cơ cũng phải tầm tw rồi | Y20: [1 Ung] @CápTần: Tầm tháng sau là thấy quyền linh ở Mỹ rồi, khoe tịch đại bàng. | Z20: [1 Ung] @ipodgen2: Ủa dm hãng nó cung cấp đủ giấy chứng nhận thì nhận job quảng cáo thôi. Chứ ko lẽ phải cầm sản phẩm đi xét nghiệm ah , trách nhiệm của cơ quan chức năng đâu mà đổ lên người quảng cáo
A21: 20 | B21: Bầu cử Tổng thống Brazil: Hai ứng cử viên bám đuổi sít sao | C21: https://baotintuc.vn/bau-cu-tong-thong-brazil-hai-ung-cu-vien-bam-duoi-sit-sao-post1391253.html | D21: https://voz.vn/t/bau-cu-tong-thong-brazil-hai-ung-cu-vien-bam-duoi-sit-sao.1285496/ | E21: 5 | F21: 0
